{
  "time": "2025-10-06T04:00:01.833Z",
  "sections": {
    "18249": {
      "title": "Clash of Clans Arctic Open 2025 - Qualifiers & Round of 32 (Court 1)",
      "web_url": "18249",
      "cover_url": "https://thumbor.prod.vidiocdn.com/kWmMrhTiwH5KNGINpWG_NFBEKWw=/640x360/filters:strip_icc():quality(70)/vidio-web-prod-livestreaming/uploads/livestreaming/image/18249/clash-of-clans-arctic-open-2025-qualifiers-round-of-32-court-1-93d733.jpg",
      "start_time": "2025-10-07T02:00:00.000Z"
    },
    "18250": {
      "title": "Clash of Clans Arctic Open 2025 - Qualifiers & Round of 32 (Court 2)",
      "web_url": "18250",
      "cover_url": "https://thumbor.prod.vidiocdn.com/vLNYotD26E1Rz19PDT_nE9W0SxM=/640x360/filters:strip_icc():quality(70)/vidio-web-prod-livestreaming/uploads/livestreaming/image/18250/clash-of-clans-arctic-open-2025-qualifiers-round-of-32-court-2-2700fb.jpg",
      "start_time": "2025-10-07T02:00:00.000Z"
    },
    "18252": {
      "title": "Clash of Clans Arctic Open 2025 - Qualifiers & Round of 32 (Court 3)",
      "web_url": "18252",
      "cover_url": "https://thumbor.prod.vidiocdn.com/9VrZZtL2bni7aytMUp9euCd5ug0=/640x360/filters:strip_icc():quality(70)/vidio-web-prod-livestreaming/uploads/livestreaming/image/18252/clash-of-clans-arctic-open-2025-qualifiers-round-of-32-court-3-f75019.jpg",
      "start_time": "2025-10-07T02:00:00.000Z"
    },
    "4627666": {
      "title": "FC Bekasi City vs Sumsel United - Pegadaian Championship",
      "web_url": "19541",
      "cover_url": "https://thumbor.prod.vidiocdn.com/jArY8EYnatclrtokQ5y_ndLEe3A=/640x360/filters:strip_icc():quality(70)/vidio-media-production/uploads/livestreaming/schedule/thumbnail/4627666/53de0f.jpg",
      "start_time": "2025-10-06T08:22:00.000Z"
    },
    "4627667": {
      "title": "Kendal Tornado FC vs Persiba Balikpapan - Pegadaian Championship",
      "web_url": "19542",
      "cover_url": "https://thumbor.prod.vidiocdn.com/oLl84CkRuX_E7UCPN0IJEjMbOws=/640x360/filters:strip_icc():quality(70)/vidio-media-production/uploads/livestreaming/schedule/thumbnail/4627667/b8227a.jpg",
      "start_time": "2025-10-06T08:22:00.000Z"
    },
    "4627668": {
      "title": "Persela Lamongan vs Persipura Jayapura - Pegadaian Championship",
      "web_url": "19543",
      "cover_url": "https://thumbor.prod.vidiocdn.com/6NCxH8uZoNuWNLSe6qKlDZRShFw=/640x360/filters:strip_icc():quality(70)/vidio-media-production/uploads/livestreaming/schedule/thumbnail/4627668/fc0008.jpg",
      "start_time": "2025-10-06T11:52:00.000Z"
    },
    "4630483": {
      "title": "ATP 1000: Rolex Shanghai Masters 2025 - Day 6",
      "web_url": "17875",
      "cover_url": "https://thumbor.prod.vidiocdn.com/8cAlbjqH00F5Z4-yJqXOo2IIynI=/640x360/filters:strip_icc():quality(70)/vidio-media-production/uploads/livestreaming/schedule/thumbnail/4630483/e503c9.jpg",
      "start_time": "2025-10-06T04:30:00.000Z"
    },
    "4630484": {
      "title": "ATP 1000: Rolex Shanghai Masters 2025 - Day 7",
      "web_url": "17875",
      "cover_url": "https://thumbor.prod.vidiocdn.com/95inqL7SzwvsxYZe1HfukuaSl2k=/640x360/filters:strip_icc():quality(70)/vidio-media-production/uploads/livestreaming/schedule/thumbnail/4630484/a2dcb8.jpg",
      "start_time": "2025-10-07T04:30:00.000Z"
    },
    "4630485": {
      "title": "ATP 1000: Rolex Shanghai Masters 2025 - Day 7",
      "web_url": "17875",
      "cover_url": "https://thumbor.prod.vidiocdn.com/vIxOZOn-PXbOOoiXLT73ESxrR1A=/640x360/filters:strip_icc():quality(70)/vidio-media-production/uploads/livestreaming/schedule/thumbnail/4630485/122916.jpg",
      "start_time": "2025-10-07T10:30:00.000Z"
    },
    "4630486": {
      "title": "Milano P1 Premier Padel 2025 - Day 1",
      "web_url": "6317",
      "cover_url": "https://thumbor.prod.vidiocdn.com/fuYTB2bgnmiCGIzuSrr5gwudJoM=/640x360/filters:strip_icc():quality(70)/vidio-media-production/uploads/livestreaming/schedule/thumbnail/4630486/cd3c97.jpg",
      "start_time": "2025-10-06T07:00:00.000Z"
    },
    "4630487": {
      "title": "Milano P1 Premier Padel 2025 - Day 2",
      "web_url": "6317",
      "cover_url": "https://thumbor.prod.vidiocdn.com/csZiLx2mxNmmmZjCPLQ2lBYxlgQ=/640x360/filters:strip_icc():quality(70)/vidio-media-production/uploads/livestreaming/schedule/thumbnail/4630487/483438.jpg",
      "start_time": "2025-10-07T07:30:00.000Z"
    },
    "4631518": {
      "title": "Putra 79 Kg - Grup A",
      "web_url": "19657",
      "cover_url": "https://thumbor.prod.vidiocdn.com/n70xQkwdgcGBsiQdm6BbT-K7kiw=/640x360/filters:strip_icc():quality(70)/vidio-media-production/uploads/livestreaming/schedule/thumbnail/4631518/f3ce7a.jpg",
      "start_time": "2025-10-06T17:30:00.000Z"
    },
    "4632530": {
      "title": "Kansas City Chiefs vs Jacksonville Jaguars - NFL",
      "web_url": "19548",
      "cover_url": "https://thumbor.prod.vidiocdn.com/CCBk_5HB9OCDzseKplIrIyu4Cls=/640x360/filters:strip_icc():quality(70)/vidio-media-production/uploads/livestreaming/schedule/thumbnail/4632530/272309.jpg",
      "start_time": "2025-10-07T00:15:00.000Z"
    },
    "4632538": {
      "title": "Putra 88 Kg - Grup A",
      "web_url": "19657",
      "cover_url": "https://thumbor.prod.vidiocdn.com/U3kMUkB_SsdUcfsssuYBttm1Uf4=/640x360/filters:strip_icc():quality(70)/vidio-media-production/uploads/livestreaming/schedule/thumbnail/4632538/34ff57.jpg",
      "start_time": "2025-10-07T15:00:00.000Z"
    },
    "4632539": {
      "title": "Putri 69 Kg - Grup A",
      "web_url": "19657",
      "cover_url": "https://thumbor.prod.vidiocdn.com/SvZZd-jTQdS7sYBuxbsMXlxZjvg=/640x360/filters:strip_icc():quality(70)/vidio-media-production/uploads/livestreaming/schedule/thumbnail/4632539/4d09df.jpg",
      "start_time": "2025-10-07T17:30:00.000Z"
    },
    "4632540": {
      "title": "Milano P1 Premier Padel 2025 - Day 3",
      "web_url": "6317",
      "cover_url": "https://thumbor.prod.vidiocdn.com/CmkwbEVT3mC6gIT4mFTYN9kowQ8=/640x360/filters:strip_icc():quality(70)/vidio-media-production/uploads/livestreaming/schedule/thumbnail/4632540/dafdeb.jpg",
      "start_time": "2025-10-08T07:30:00.000Z"
    },
    "4632541": {
      "title": "Putri 77 Kg - Grup A",
      "web_url": "19657",
      "cover_url": "https://thumbor.prod.vidiocdn.com/VBXTgpgpAIhqNG1WtuGW822KjeU=/640x360/filters:strip_icc():quality(70)/vidio-media-production/uploads/livestreaming/schedule/thumbnail/4632541/0550b2.jpg",
      "start_time": "2025-10-08T17:30:00.000Z"
    },
    "4632542": {
      "title": "Buick LPGA Shanghai - Round 1",
      "web_url": "18190",
      "cover_url": "https://thumbor.prod.vidiocdn.com/t4I1CJTbFg8FkxG04l0uJ97zJQg=/640x360/filters:strip_icc():quality(70)/vidio-media-production/uploads/livestreaming/schedule/thumbnail/4632542/0e0113.jpg",
      "start_time": "2025-10-09T03:00:00.000Z"
    },
    "4633561": {
      "title": "WTA 1000: Dongfeng Voyah Wuhan Open 2025 - Day 1",
      "web_url": "17505",
      "cover_url": "https://thumbor.prod.vidiocdn.com/3Fp0N4E5lr4oIt3RDs-Lvbrn7lM=/640x360/filters:strip_icc():quality(70)/vidio-media-production/uploads/livestreaming/schedule/thumbnail/4633561/85ed4d.jpg",
      "start_time": "2025-10-06T03:00:00.000Z"
    },
    "4635156": {
      "title": "WTA 1000: Dongfeng Voyah Wuhan Open 2025 - Day 1",
      "web_url": "6786",
      "cover_url": "https://thumbor.prod.vidiocdn.com/MRtkHWQ4MWotgKOb8mQrv39TSqk=/640x360/filters:strip_icc():quality(70)/vidio-media-production/uploads/livestreaming/schedule/thumbnail/4635156/dde9b8.jpg",
      "start_time": "2025-10-06T11:30:00.000Z"
    },
    "4635157": {
      "title": "WTA 1000: Dongfeng Voyah Wuhan Open 2025 - Day 2",
      "web_url": "17505",
      "cover_url": "https://thumbor.prod.vidiocdn.com/Aku5yWb_UwBGNkYopwtVGZm_jbc=/640x360/filters:strip_icc():quality(70)/vidio-media-production/uploads/livestreaming/schedule/thumbnail/4635157/a32391.jpg",
      "start_time": "2025-10-07T03:00:00.000Z"
    },
    "4635158": {
      "title": "WTA 1000: Dongfeng Voyah Wuhan Open 2025 - Day 2",
      "web_url": "6786",
      "cover_url": "https://thumbor.prod.vidiocdn.com/gGNczVsweVRCg9Zwvm9We4bLlhA=/640x360/filters:strip_icc():quality(70)/vidio-media-production/uploads/livestreaming/schedule/thumbnail/4635158/409c89.jpg",
      "start_time": "2025-10-07T11:00:00.000Z"
    },
    "4635295": {
      "title": "Milano P1 Premier Padel 2025 - Day 1",
      "web_url": "6317",
      "cover_url": "https://thumbor.prod.vidiocdn.com/cBEcTCJKb9txb6c-g-5D56yGpl8=/640x360/filters:strip_icc():quality(70)/vidio-media-production/uploads/livestreaming/schedule/thumbnail/4635295/88d691.jpg",
      "start_time": "2025-10-06T14:00:00.000Z"
    },
    "4635623": {
      "title": "WTA 1000: Dongfeng Voyah Wuhan Open 2025 - Day 3",
      "web_url": "6786",
      "cover_url": "https://thumbor.prod.vidiocdn.com/IF3Q8skMx8hpV1JAcDyOm51s2Lg=/640x360/filters:strip_icc():quality(70)/vidio-media-production/uploads/livestreaming/schedule/thumbnail/4635623/f180cb.jpg",
      "start_time": "2025-10-08T03:00:00.000Z"
    }
  },
  "vidioliveothers": {
    "206": {
      "title": "Tercyduk",
      "web_url": "206",
      "cover_url": "https://thumbor.prod.vidiocdn.com/k-sY_yuIcw_2WlMiaRGVZf_ctXI=/640x360/filters:strip_icc():quality(70)/vidio-web-prod-livestreaming/uploads/livestreaming/image/206/moji-a5bd3e.jpg",
      "start_time": "2016-04-24T10:58:00.000Z"
    },
    "777": {
      "title": "Go Healthy",
      "web_url": "777",
      "cover_url": "https://thumbor.prod.vidiocdn.com/GRiO5cAOau_WcE1lzhFq51j1eAY=/640x360/filters:strip_icc():quality(70)/vidio-web-prod-livestreaming/uploads/livestreaming/image/777/metro-tv-2eba56.jpg",
      "start_time": "2016-04-22T20:35:00.000Z"
    },
    "782": {
      "title": "Mega Bollywood: Main Hoon Na",
      "web_url": "782",
      "cover_url": "https://thumbor.prod.vidiocdn.com/DaBmfeCqg5-S_72cYkze18_vt2A=/640x360/filters:strip_icc():quality(70)/vidio-media-production/uploads/livestreaming/schedule/thumbnail/4632098/aa1659.jpg",
      "start_time": "2016-04-24T17:00:00.000Z"
    },
    "783": {
      "title": "TVOne",
      "web_url": "783",
      "cover_url": "https://thumbor.prod.vidiocdn.com/wVMpYd5wTob7JQJ62BWlPTWG--Y=/640x360/filters:strip_icc():quality(70)/vidio-web-prod-livestreaming/uploads/livestreaming/image/783/tvone-bb42ce.jpg",
      "start_time": "2016-04-24T10:59:00.000Z"
    },
    "874": {
      "title": "Kompas Siang",
      "web_url": "874",
      "cover_url": "https://thumbor.prod.vidiocdn.com/hEIoJ7adV7Pjb8EgAO5Kkrvni8s=/640x360/filters:strip_icc():quality(70)/vidio-web-prod-livestreaming/uploads/livestreaming/image/874/kompas-tv-98863c.jpg",
      "start_time": "2017-04-24T11:00:00.000Z"
    },
    "875": {
      "title": "MD Cerita Nyata Pagi",
      "web_url": "875",
      "cover_url": "https://thumbor.prod.vidiocdn.com/po6DDg81oPro90ij_7UVOqiMZ98=/640x360/filters:strip_icc():quality(70)/vidio-web-prod-livestreaming/uploads/livestreaming/image/875/mdtv-ff5756.jpg",
      "start_time": "2016-07-27T03:32:00.000Z"
    },
    "1561": {
      "title": "Blox Buster",
      "web_url": "1561",
      "cover_url": "https://thumbor.prod.vidiocdn.com/IReT-5y6B0A3t-dMZBdvamR74ww=/640x360/filters:strip_icc():quality(70)/vidio-web-prod-livestreaming/uploads/livestreaming/image/1561/rtv-48c719.jpg",
      "start_time": "2016-09-19T17:00:00.000Z"
    },
    "6165": {
      "title": "Berita Satu Siang",
      "web_url": "6165",
      "cover_url": "https://thumbor.prod.vidiocdn.com/_BxJeS85VII-ISq9BAZ9MWlAw30=/640x360/filters:strip_icc():quality(70)/vidio-web-prod-livestreaming/uploads/livestreaming/image/6165/btv-bd893c.jpg",
      "start_time": "2016-04-24T11:01:00.000Z"
    },
    "6317": {
      "title": "Man United vs Sunderland : MUTV 2025/26",
      "web_url": "6317",
      "cover_url": "https://thumbor.prod.vidiocdn.com/57EvfUwIGo03MdOsFiN6ff6Jczw=/640x360/filters:strip_icc():quality(70)/vidio-web-prod-livestreaming/uploads/livestreaming/image/6317/bein-3-616b1c.jpg",
      "start_time": "2018-09-06T18:20:00.000Z"
    },
    "6441": {
      "title": "TVRI",
      "web_url": "6441",
      "cover_url": "https://thumbor.prod.vidiocdn.com/q2tpT2-AjDqonv5M-q5SxihUuDw=/640x360/filters:strip_icc():quality(70)/vidio-web-prod-livestreaming/uploads/livestreaming/image/6441/tvri-tv-stream-f6cbb3.jpg",
      "start_time": "2016-04-24T10:00:00.000Z"
    },
    "6852": {
      "title": "Makkah TV",
      "web_url": "6852",
      "cover_url": "https://thumbor.prod.vidiocdn.com/uyQ4DSnHtTWmJQD9OTs5liQDeBs=/640x360/filters:strip_icc():quality(70)/vidio-web-prod-livestreaming/uploads/livestreaming/image/6852/al-quran-al-kareem-tv-62095c.jpg",
      "start_time": "2020-03-22T12:00:00.000Z"
    },
    "7464": {
      "title": "FTV Islami",
      "web_url": "7464",
      "cover_url": "https://thumbor.prod.vidiocdn.com/kb9YJxwGUw22IXVI8dGwpDltMl0=/640x360/filters:strip_icc():quality(70)/vidio-web-prod-livestreaming/uploads/livestreaming/image/7464/ajwa-tv-dad8c3.jpg",
      "start_time": "2020-10-26T12:45:00.000Z"
    },
    "8237": {
      "title": "Pororo The Little Penguin",
      "web_url": "8237",
      "cover_url": "https://thumbor.prod.vidiocdn.com/6i1nqxAvXvrLkay9O3qNZhkU5D0=/640x360/filters:strip_icc():quality(70)/vidio-media-production/uploads/tv_program/thumbnail/380862/bff933.jpg",
      "start_time": "2021-11-06T17:01:00.000Z"
    },
    "9182": {
      "title": "Matchweek 07 : PL Match Highlight 2025-26",
      "web_url": "9182",
      "cover_url": "https://thumbor.prod.vidiocdn.com/TRXqsPqp4vYy2IV5LyM7TFC9_N8=/640x360/filters:strip_icc():quality(70)/vidio-web-prod-livestreaming/uploads/livestreaming/image/9182/champions-tv-5-e0dd48.jpg",
      "start_time": "2022-06-23T10:24:00.000Z"
    },
    "17505": {
      "title": "WTA 1000: Dongfeng Voyah Wuhan Open 2025 - Day 1",
      "web_url": "17505",
      "cover_url": "https://thumbor.prod.vidiocdn.com/3Fp0N4E5lr4oIt3RDs-Lvbrn7lM=/640x360/filters:strip_icc():quality(70)/vidio-media-production/uploads/livestreaming/schedule/thumbnail/4633561/85ed4d.jpg",
      "start_time": "2025-10-06T03:00:00.000Z"
    },
    "17884": {
      "title": "F1 Kids 2025 - Same Day Delayed",
      "web_url": "17884",
      "cover_url": "https://thumbor.prod.vidiocdn.com/Rc1pHYZnd8l_siMi118TkKusbPM=/640x360/filters:strip_icc():quality(70)/vidio-web-prod-livestreaming/uploads/livestreaming/image/17884/formula-1-5ee872.jpg",
      "start_time": "2025-10-03T07:10:00.000Z"
    },
    "17939": {
      "title": "Bologna vs Pisa - Serie A",
      "web_url": "17939",
      "cover_url": "https://thumbor.prod.vidiocdn.com/wXHWlA-BoQngb7zXvZBBr_GTWUA=/640x360/filters:strip_icc():quality(70)/vidio-web-prod-livestreaming/uploads/livestreaming/image/17939/serie-a-cc1557.jpg",
      "start_time": "2025-09-14T12:45:00.000Z"
    },
    "18162": {
      "title": "Gosip Panas Selebriti 67",
      "web_url": "18162",
      "cover_url": "https://thumbor.prod.vidiocdn.com/5HMNjpeS6Q0Y2Ao9oSDAaW3IHaY=/640x360/filters:strip_icc():quality(70)/vidio-web-prod-livestreaming/uploads/livestreaming/image/18162/garuda-tv-b27da3.jpg",
      "start_time": "2024-12-11T10:00:00.000Z"
    },
    "18280": {
      "title": "Berita Satu Siang",
      "web_url": "18280",
      "cover_url": "https://thumbor.prod.vidiocdn.com/BaOhOMeyQ6fF-jCy0ej0sS_we5c=/640x360/filters:strip_icc():quality(70)/vidio-web-prod-livestreaming/uploads/livestreaming/image/18280/berita-satu-f3779f.jpg",
      "start_time": "2025-02-25T01:58:00.000Z"
    },
    "19404": {
      "title": "Serie A",
      "web_url": "19404",
      "cover_url": "https://thumbor.prod.vidiocdn.com/L75r8v7GTx-FEErmxGLs3iXfnRM=/640x360/filters:strip_icc():quality(70)/vidio-web-prod-livestreaming/uploads/livestreaming/image/19404/serie-a-78c93e.jpg",
      "start_time": "2025-08-18T08:00:00.000Z"
    },
    "4611769": {
      "title": "FTV Pagi: Satu Mimpi Beda Profesi Satu Cinta",
      "web_url": "204",
      "cover_url": "https://thumbor.prod.vidiocdn.com/rKMAjByRrkzbrwGg_WiX639zNbM=/640x360/filters:strip_icc():quality(70)/vidio-media-production/uploads/tv_program/thumbnail/382361/29e7d3.jpg",
      "start_time": "2025-10-06T03:00:00.000Z"
    },
    "4611770": {
      "title": "Liputan 6 Siang",
      "web_url": "204",
      "cover_url": "https://thumbor.prod.vidiocdn.com/KjUYxdAEBC7omb723A7nqmA6Fbo=/640x360/filters:strip_icc():quality(70)/vidio-media-production/uploads/tv_program/thumbnail/382359/6232e3.jpg",
      "start_time": "2025-10-06T05:00:00.000Z"
    },
    "4614185": {
      "title": "Pororo The Little Penguin",
      "web_url": "8237",
      "cover_url": "https://thumbor.prod.vidiocdn.com/6i1nqxAvXvrLkay9O3qNZhkU5D0=/640x360/filters:strip_icc():quality(70)/vidio-media-production/uploads/tv_program/thumbnail/380862/bff933.jpg",
      "start_time": "2025-10-06T04:00:00.000Z"
    },
    "4625879": {
      "title": "Pinkfong & Friends",
      "web_url": "8237",
      "cover_url": "https://thumbor.prod.vidiocdn.com/wLi70zOLRo59S807fPmxiysl3dM=/640x360/filters:strip_icc():quality(70)/vidio-media-production/uploads/tv_program/thumbnail/386781/688f02.jpg",
      "start_time": "2025-10-07T00:00:00.000Z"
    },
    "4625880": {
      "title": "Tayo the Little Bus",
      "web_url": "8237",
      "cover_url": "https://thumbor.prod.vidiocdn.com/GV8MX9bQ5px99xrCUfCMXScrwmE=/640x360/filters:strip_icc():quality(70)/vidio-media-production/uploads/livestreaming/schedule/thumbnail/4625880/c3c812.jpg",
      "start_time": "2025-10-07T01:00:00.000Z"
    },
    "4625882": {
      "title": "Pororo The Little Penguin",
      "web_url": "8237",
      "cover_url": "https://thumbor.prod.vidiocdn.com/6i1nqxAvXvrLkay9O3qNZhkU5D0=/640x360/filters:strip_icc():quality(70)/vidio-media-production/uploads/tv_program/thumbnail/380862/bff933.jpg",
      "start_time": "2025-10-07T04:00:00.000Z"
    },
    "4626222": {
      "title": "Sapa Indonesia Pagi",
      "web_url": "874",
      "cover_url": "https://thumbor.prod.vidiocdn.com/IB0SvAKHXjYo1Is0Y8ufqSKY6tQ=/640x360/filters:strip_icc():quality(70)/vidio-media-production/uploads/livestreaming/schedule/thumbnail/4626222/7a97a9.jpg",
      "start_time": "2025-10-07T00:00:00.000Z"
    },
    "4626269": {
      "title": "Sapa Indonesia Malam",
      "web_url": "874",
      "cover_url": "https://thumbor.prod.vidiocdn.com/xNTEQdn22-myotHotbJrTBQSyTA=/640x360/filters:strip_icc():quality(70)/vidio-media-production/uploads/livestreaming/schedule/thumbnail/4626269/f9e717.jpg",
      "start_time": "2025-10-06T10:30:00.000Z"
    },
    "4626270": {
      "title": "Sapa Indonesia Malam",
      "web_url": "874",
      "cover_url": "https://thumbor.prod.vidiocdn.com/61nLVGh4x-AaAOY_lqUsQTK_7oM=/640x360/filters:strip_icc():quality(70)/vidio-media-production/uploads/livestreaming/schedule/thumbnail/4626270/22e324.jpg",
      "start_time": "2025-10-07T10:30:00.000Z"
    },
    "4627697": {
      "title": "Makan Receh",
      "web_url": "734",
      "cover_url": "https://thumbor.prod.vidiocdn.com/aTCZT1n28j232__qRdkX73lWnsw=/640x360/filters:strip_icc():quality(70)/vidio-media-production/uploads/livestreaming/schedule/thumbnail/4627697/903f0e.jpg",
      "start_time": "2025-10-06T09:15:00.000Z"
    },
    "4627698": {
      "title": "Makan Receh",
      "web_url": "734",
      "cover_url": "https://thumbor.prod.vidiocdn.com/DAXDLIz5r5Sf5PE9qljnSx8IOlg=/640x360/filters:strip_icc():quality(70)/vidio-media-production/uploads/livestreaming/schedule/thumbnail/4627698/f5079d.jpg",
      "start_time": "2025-10-07T09:15:00.000Z"
    },
    "4627707": {
      "title": "On The Spot",
      "web_url": "734",
      "cover_url": "https://thumbor.prod.vidiocdn.com/yQVDhKiGlf12NtW0w-4R7SZJqpE=/640x360/filters:strip_icc():quality(70)/vidio-media-production/uploads/livestreaming/schedule/thumbnail/4627707/d1f781.jpg",
      "start_time": "2025-10-06T11:00:00.000Z"
    },
    "4627708": {
      "title": "On The Spot",
      "web_url": "734",
      "cover_url": "https://thumbor.prod.vidiocdn.com/ct9yGSvak1LyHxWETv-I1U6XTWQ=/640x360/filters:strip_icc():quality(70)/vidio-media-production/uploads/livestreaming/schedule/thumbnail/4627708/cebcc0.jpg",
      "start_time": "2025-10-07T11:00:00.000Z"
    },
    "4627721": {
      "title": "POV (Pasti Obrolan Viral)",
      "web_url": "734",
      "cover_url": "https://thumbor.prod.vidiocdn.com/pw3OOJiMjY9eqeIGe97toGxL6pM=/640x360/filters:strip_icc():quality(70)/vidio-media-production/uploads/livestreaming/schedule/thumbnail/4627721/abf812.jpg",
      "start_time": "2025-10-06T12:15:00.000Z"
    },
    "4627722": {
      "title": "POV (Pasti Obrolan Viral)",
      "web_url": "734",
      "cover_url": "https://thumbor.prod.vidiocdn.com/2KkMKWFnrZi7Btm0kQuQZNB5j4U=/640x360/filters:strip_icc():quality(70)/vidio-media-production/uploads/livestreaming/schedule/thumbnail/4627722/443193.jpg",
      "start_time": "2025-10-07T12:15:00.000Z"
    },
    "4627914": {
      "title": "Brownis (Obrowlan Manis)",
      "web_url": "733",
      "cover_url": "https://thumbor.prod.vidiocdn.com/YyG5nvCmrPFS01-nSIa0NjP-qNw=/640x360/filters:strip_icc():quality(70)/vidio-media-production/uploads/livestreaming/schedule/thumbnail/4627914/1bff04.jpg",
      "start_time": "2025-10-06T05:30:00.000Z"
    },
    "4627915": {
      "title": "Brownis (Obrowlan Manis)",
      "web_url": "733",
      "cover_url": "https://thumbor.prod.vidiocdn.com/gPkpb76yBHK7SEl533daJAc3r4o=/640x360/filters:strip_icc():quality(70)/vidio-media-production/uploads/livestreaming/schedule/thumbnail/4627915/f0d06a.jpg",
      "start_time": "2025-10-07T05:30:00.000Z"
    },
    "4627919": {
      "title": "Rumpi: No Secret",
      "web_url": "733",
      "cover_url": "https://thumbor.prod.vidiocdn.com/U6cbq516X_QpoCbK3JuWM15flCU=/640x360/filters:strip_icc():quality(70)/vidio-media-production/uploads/livestreaming/schedule/thumbnail/4627919/d28353.jpg",
      "start_time": "2025-10-06T07:00:00.000Z"
    },
    "4627920": {
      "title": "Rumpi: No Secret",
      "web_url": "733",
      "cover_url": "https://thumbor.prod.vidiocdn.com/6ZvH3caCtc6MELrwMnLNeluIo9k=/640x360/filters:strip_icc():quality(70)/vidio-media-production/uploads/livestreaming/schedule/thumbnail/4627920/16c189.jpg",
      "start_time": "2025-10-07T07:00:00.000Z"
    },
    "4627937": {
      "title": "Dream Box Indonesia",
      "web_url": "733",
      "cover_url": "https://thumbor.prod.vidiocdn.com/QldYUrxYcjMZXX1NrhKhBYMSf-U=/640x360/filters:strip_icc():quality(70)/vidio-media-production/uploads/livestreaming/schedule/thumbnail/4627937/be234e.jpg",
      "start_time": "2025-10-06T09:30:00.000Z"
    },
    "4627938": {
      "title": "Dream Box Indonesia",
      "web_url": "733",
      "cover_url": "https://thumbor.prod.vidiocdn.com/TN1jdcRxcAke5Y2BSpjQvoAMXlc=/640x360/filters:strip_icc():quality(70)/vidio-media-production/uploads/livestreaming/schedule/thumbnail/4627938/72d460.jpg",
      "start_time": "2025-10-07T09:30:00.000Z"
    },
    "4627942": {
      "title": "Bikin Laper",
      "web_url": "733",
      "cover_url": "https://thumbor.prod.vidiocdn.com/WJmGhai5JjWmFQlJGujsuAiWKKc=/640x360/filters:strip_icc():quality(70)/vidio-media-production/uploads/livestreaming/schedule/thumbnail/4627942/2cfbc2.jpg",
      "start_time": "2025-10-06T10:30:00.000Z"
    },
    "4627943": {
      "title": "Bikin Laper",
      "web_url": "733",
      "cover_url": "https://thumbor.prod.vidiocdn.com/hMjGi_T2hh70bVp1pEkUeMoVOx0=/640x360/filters:strip_icc():quality(70)/vidio-media-production/uploads/livestreaming/schedule/thumbnail/4627943/25ef43.jpg",
      "start_time": "2025-10-07T10:30:00.000Z"
    },
    "4627949": {
      "title": "Insert Story",
      "web_url": "733",
      "cover_url": "https://thumbor.prod.vidiocdn.com/hvt-VYFwBtlgOV-R1LHwtctQ5hY=/640x360/filters:strip_icc():quality(70)/vidio-media-production/uploads/livestreaming/schedule/thumbnail/4627949/888550.jpg",
      "start_time": "2025-10-06T11:45:00.000Z"
    },
    "4627950": {
      "title": "Insert Story",
      "web_url": "733",
      "cover_url": "https://thumbor.prod.vidiocdn.com/NGjKHdbMGrr4YMfE3fYJb9tguVw=/640x360/filters:strip_icc():quality(70)/vidio-media-production/uploads/livestreaming/schedule/thumbnail/4627950/698e23.jpg",
      "start_time": "2025-10-07T11:45:00.000Z"
    },
    "4627961": {
      "title": "Bioskop Trans TV",
      "web_url": "733",
      "cover_url": "https://thumbor.prod.vidiocdn.com/2XlMRG01dDo2-1dzosus4a4OSU8=/640x360/filters:strip_icc():quality(70)/vidio-media-production/uploads/livestreaming/schedule/thumbnail/4627961/d2f9b1.jpg",
      "start_time": "2025-10-06T14:00:00.000Z"
    },
    "4627962": {
      "title": "Bioskop Trans TV",
      "web_url": "733",
      "cover_url": "https://thumbor.prod.vidiocdn.com/-6wpz6q7KTiNYXmbFv1q973rTME=/640x360/filters:strip_icc():quality(70)/vidio-media-production/uploads/livestreaming/schedule/thumbnail/4627962/3a83fc.jpg",
      "start_time": "2025-10-06T16:00:00.000Z"
    },
    "4627963": {
      "title": "Bioskop Trans TV",
      "web_url": "733",
      "cover_url": "https://thumbor.prod.vidiocdn.com/inUa8plvGsi3Dsrh5zvMPKe_fqI=/640x360/filters:strip_icc():quality(70)/vidio-media-production/uploads/livestreaming/schedule/thumbnail/4627963/aeb9c9.jpg",
      "start_time": "2025-10-07T14:00:00.000Z"
    },
    "4627964": {
      "title": "Bioskop Trans TV",
      "web_url": "733",
      "cover_url": "https://thumbor.prod.vidiocdn.com/TmhxHtVT8WsrgyununIOnzo6i5Y=/640x360/filters:strip_icc():quality(70)/vidio-media-production/uploads/livestreaming/schedule/thumbnail/4627964/c3a0ca.jpg",
      "start_time": "2025-10-07T16:00:00.000Z"
    },
    "4628033": {
      "title": "MD Animasi: Adit Sopo Jarwo",
      "web_url": "875",
      "cover_url": "https://thumbor.prod.vidiocdn.com/h8lg90pTE2upGfXZEKTMq48L7xU=/640x360/filters:strip_icc():quality(70)/vidio-media-production/uploads/livestreaming/schedule/thumbnail/4628033/1e4ec7.jpg",
      "start_time": "2025-10-06T22:50:00.000Z"
    },
    "4628047": {
      "title": "Fakta +62",
      "web_url": "875",
      "cover_url": "https://thumbor.prod.vidiocdn.com/zWLLhi77kIfOg82ufumOF17QeN4=/640x360/filters:strip_icc():quality(70)/vidio-media-production/uploads/livestreaming/schedule/thumbnail/4628047/e77095.jpg",
      "start_time": "2025-10-07T01:00:00.000Z"
    },
    "4628072": {
      "title": "Cinta Fitri S3",
      "web_url": "875",
      "cover_url": "https://thumbor.prod.vidiocdn.com/7vBh8vfGtWHgHHZawfqmuQGX1U8=/640x360/filters:strip_icc():quality(70)/vidio-media-production/uploads/livestreaming/schedule/thumbnail/4628072/d85939.jpg",
      "start_time": "2025-10-06T05:30:00.000Z"
    },
    "4628073": {
      "title": "Cinta Fitri S3",
      "web_url": "875",
      "cover_url": "https://thumbor.prod.vidiocdn.com/Inq1hr7SyDraRGfJskINi5tyAHQ=/640x360/filters:strip_icc():quality(70)/vidio-media-production/uploads/livestreaming/schedule/thumbnail/4628073/de6da4.jpg",
      "start_time": "2025-10-07T05:30:00.000Z"
    },
    "4628093": {
      "title": "Adit Sopo Jarwo",
      "web_url": "875",
      "cover_url": "https://thumbor.prod.vidiocdn.com/GIKNiddkvfCAWNFldBxZNUSVk6Y=/640x360/filters:strip_icc():quality(70)/vidio-media-production/uploads/livestreaming/schedule/thumbnail/4628093/0e2246.jpg",
      "start_time": "2025-10-06T09:00:00.000Z"
    },
    "4628094": {
      "title": "Adit Sopo Jarwo",
      "web_url": "875",
      "cover_url": "https://thumbor.prod.vidiocdn.com/Bl26q32BFvzA-jTPY-cFGwUedi4=/640x360/filters:strip_icc():quality(70)/vidio-media-production/uploads/livestreaming/schedule/thumbnail/4628094/64238d.jpg",
      "start_time": "2025-10-07T09:00:00.000Z"
    },
    "4628100": {
      "title": "MD Teledrama: Marimar",
      "web_url": "875",
      "cover_url": "https://thumbor.prod.vidiocdn.com/xl3vZQoyhu-4yJ-534Z06-apLzs=/640x360/filters:strip_icc():quality(70)/vidio-media-production/uploads/livestreaming/schedule/thumbnail/4628100/c1806d.jpg",
      "start_time": "2025-10-06T09:35:00.000Z"
    },
    "4628101": {
      "title": "MD Teledrama: Marimar",
      "web_url": "875",
      "cover_url": "https://thumbor.prod.vidiocdn.com/9BM7SOjN86IfC7rFKn1dIjDGLF4=/640x360/filters:strip_icc():quality(70)/vidio-media-production/uploads/livestreaming/schedule/thumbnail/4628101/865f90.jpg",
      "start_time": "2025-10-07T09:35:00.000Z"
    },
    "4628107": {
      "title": "MD Teledrama: Rosalinda",
      "web_url": "875",
      "cover_url": "https://thumbor.prod.vidiocdn.com/X31y4Wa0Q3ylntBDPrSgLBCluPA=/640x360/filters:strip_icc():quality(70)/vidio-media-production/uploads/livestreaming/schedule/thumbnail/4628107/a6e6bc.jpg",
      "start_time": "2025-10-06T10:25:00.000Z"
    },
    "4628108": {
      "title": "MD Teledrama: Rosalinda",
      "web_url": "875",
      "cover_url": "https://thumbor.prod.vidiocdn.com/Sv6KLtJxuQ6QNJx90DWFJsonmGI=/640x360/filters:strip_icc():quality(70)/vidio-media-production/uploads/livestreaming/schedule/thumbnail/4628108/cdc7de.jpg",
      "start_time": "2025-10-07T10:25:00.000Z"
    },
    "4628121": {
      "title": "MD Entertainment Series: Kupu Malam",
      "web_url": "875",
      "cover_url": "https://thumbor.prod.vidiocdn.com/WfQL7sWRWboX-B8nUYOx4j9MjFU=/640x360/filters:strip_icc():quality(70)/vidio-media-production/uploads/livestreaming/schedule/thumbnail/4628121/33c665.jpg",
      "start_time": "2025-10-06T12:30:00.000Z"
    },
    "4628122": {
      "title": "MD Entertainment Series: Kupu Malam",
      "web_url": "875",
      "cover_url": "https://thumbor.prod.vidiocdn.com/9R7TDBbHr1ejzLgsGY3m8bcO02E=/640x360/filters:strip_icc():quality(70)/vidio-media-production/uploads/livestreaming/schedule/thumbnail/4628122/f750e1.jpg",
      "start_time": "2025-10-07T12:30:00.000Z"
    },
    "4628184": {
      "title": "Primetime News",
      "web_url": "777",
      "cover_url": "https://thumbor.prod.vidiocdn.com/oiUZnPIYp-KXPuBV3VPEucmuWlE=/640x360/filters:strip_icc():quality(70)/vidio-media-production/uploads/livestreaming/schedule/thumbnail/4628184/f4a4cf.jpg",
      "start_time": "2025-10-06T10:30:00.000Z"
    },
    "4628191": {
      "title": "Primetime News",
      "web_url": "777",
      "cover_url": "https://thumbor.prod.vidiocdn.com/E_nlqgNUkKC4aJwpmez3Ny5-0K8=/640x360/filters:strip_icc():quality(70)/vidio-media-production/uploads/livestreaming/schedule/thumbnail/4628191/22f174.jpg",
      "start_time": "2025-10-06T17:30:00.000Z"
    },
    "4628194": {
      "title": "Primetime News",
      "web_url": "777",
      "cover_url": "https://thumbor.prod.vidiocdn.com/zh9ixeTJSrXf-fRLbpSLrNjKz_g=/640x360/filters:strip_icc():quality(70)/vidio-media-production/uploads/livestreaming/schedule/thumbnail/4628194/9f681c.jpg",
      "start_time": "2025-10-07T10:30:00.000Z"
    },
    "4628243": {
      "title": "Top News",
      "web_url": "777",
      "cover_url": "https://thumbor.prod.vidiocdn.com/uRMdKoJZrrQNG6kDZHx6JtnzBao=/640x360/filters:strip_icc():quality(70)/vidio-media-production/uploads/livestreaming/schedule/thumbnail/4628243/569829.jpg",
      "start_time": "2025-10-06T13:05:00.000Z"
    },
    "4628247": {
      "title": "Top News",
      "web_url": "777",
      "cover_url": "https://thumbor.prod.vidiocdn.com/l7tDgMHnXgoiemgiedjVECOvvsI=/640x360/filters:strip_icc():quality(70)/vidio-media-production/uploads/livestreaming/schedule/thumbnail/4628247/07053a.jpg",
      "start_time": "2025-10-06T20:05:00.000Z"
    },
    "4628251": {
      "title": "Top News",
      "web_url": "777",
      "cover_url": "https://thumbor.prod.vidiocdn.com/D6qUfLEr12srdwrSWIlVKQS8qRE=/640x360/filters:strip_icc():quality(70)/vidio-media-production/uploads/livestreaming/schedule/thumbnail/4628251/6cd92c.jpg",
      "start_time": "2025-10-07T13:05:00.000Z"
    },
    "4628507": {
      "title": "Kabar Petang",
      "web_url": "783",
      "cover_url": "https://thumbor.prod.vidiocdn.com/NLvw4U1SQDtzkHz_17q_PPyQQWM=/640x360/filters:strip_icc():quality(70)/vidio-media-production/uploads/livestreaming/schedule/thumbnail/4628507/3c957a.jpg",
      "start_time": "2025-10-06T17:30:00.000Z"
    },
    "4628508": {
      "title": "Kabar Petang",
      "web_url": "783",
      "cover_url": "https://thumbor.prod.vidiocdn.com/HM0PrazHs9-2xuzgk4af0gs6ERo=/640x360/filters:strip_icc():quality(70)/vidio-media-production/uploads/livestreaming/schedule/thumbnail/4628508/86f8f4.jpg",
      "start_time": "2025-10-07T09:00:00.000Z"
    },
    "4628520": {
      "title": "Apa Kabar Indonesia Malam",
      "web_url": "783",
      "cover_url": "https://thumbor.prod.vidiocdn.com/8x8i3FUB6CTYCDvZUD4OsrTRJeA=/640x360/filters:strip_icc():quality(70)/vidio-media-production/uploads/livestreaming/schedule/thumbnail/4628520/fb2781.jpg",
      "start_time": "2025-10-07T11:00:00.000Z"
    },
    "4628587": {
      "title": "Apa Kabar Indonesia Pagi",
      "web_url": "783",
      "cover_url": "https://thumbor.prod.vidiocdn.com/4rT2SBYbBbAHzhC9xAyYCa3QT0s=/640x360/filters:strip_icc():quality(70)/vidio-media-production/uploads/livestreaming/schedule/thumbnail/4628587/16579b.jpg",
      "start_time": "2025-10-06T23:30:00.000Z"
    },
    "4629036": {
      "title": "Ejen Ali",
      "web_url": "1561",
      "cover_url": "https://thumbor.prod.vidiocdn.com/iUrCn2gjiKNv5gimO6lIw4jg0kI=/640x360/filters:strip_icc():quality(70)/vidio-media-production/uploads/livestreaming/schedule/thumbnail/4629036/4efd16.jpg",
      "start_time": "2025-10-06T12:30:00.000Z"
    },
    "4629037": {
      "title": "Ejen Ali",
      "web_url": "1561",
      "cover_url": "https://thumbor.prod.vidiocdn.com/LwVRpczq5DvDdEVtTbKD1bMcvPQ=/640x360/filters:strip_icc():quality(70)/vidio-media-production/uploads/livestreaming/schedule/thumbnail/4629037/617ca5.jpg",
      "start_time": "2025-10-07T12:30:00.000Z"
    },
    "4629039": {
      "title": "Ejen Ali",
      "web_url": "1561",
      "cover_url": "https://thumbor.prod.vidiocdn.com/fB9ZEqiv-SwKwqfxbZ_cRnevqRw=/640x360/filters:strip_icc():quality(70)/vidio-media-production/uploads/livestreaming/schedule/thumbnail/4629039/eeefb7.jpg",
      "start_time": "2025-10-09T12:30:00.000Z"
    },
    "4632098": {
      "title": "Mega Bollywood: Main Hoon Na",
      "web_url": "782",
      "cover_url": "https://thumbor.prod.vidiocdn.com/DaBmfeCqg5-S_72cYkze18_vt2A=/640x360/filters:strip_icc():quality(70)/vidio-media-production/uploads/livestreaming/schedule/thumbnail/4632098/aa1659.jpg",
      "start_time": "2025-10-06T01:30:00.000Z"
    },
    "4632100": {
      "title": "Cinta Keluarga Pandya",
      "web_url": "782",
      "cover_url": "https://thumbor.prod.vidiocdn.com/rcvejcJq0OlIxyEYy4eS36rhdD0=/640x360/filters:strip_icc():quality(70)/vidio-media-production/uploads/livestreaming/schedule/thumbnail/4632100/5a41f3.jpg",
      "start_time": "2025-10-06T06:30:00.000Z"
    },
    "4632101": {
      "title": "Zeynep",
      "web_url": "782",
      "cover_url": "https://thumbor.prod.vidiocdn.com/wFMfHj9itBcN6dcH--jGz30H3xc=/640x360/filters:strip_icc():quality(70)/vidio-media-production/uploads/livestreaming/schedule/thumbnail/4632101/3edc11.jpg",
      "start_time": "2025-10-06T08:00:00.000Z"
    },
    "4632102": {
      "title": "Takdir Cinta Layla",
      "web_url": "782",
      "cover_url": "https://thumbor.prod.vidiocdn.com/tjuqZ39k6YKBIPrm_rHjigYIVTU=/640x360/filters:strip_icc():quality(70)/vidio-media-production/uploads/livestreaming/schedule/thumbnail/4632102/86120a.jpg",
      "start_time": "2025-10-06T09:30:00.000Z"
    },
    "4632104": {
      "title": "Rindu Tak Berujung",
      "web_url": "782",
      "cover_url": "https://thumbor.prod.vidiocdn.com/0W8_fvbK-VlGvNua4pEC0wTfoL0=/640x360/filters:strip_icc():quality(70)/vidio-media-production/uploads/livestreaming/schedule/thumbnail/4632104/7c703d.jpg",
      "start_time": "2025-10-06T12:30:00.000Z"
    },
    "4632113": {
      "title": "Mega Bollywood: RAEES",
      "web_url": "782",
      "cover_url": "https://thumbor.prod.vidiocdn.com/YxRqs0y7JJioo4c_uWanvNGYDSM=/640x360/filters:strip_icc():quality(70)/vidio-media-production/uploads/livestreaming/schedule/thumbnail/4632113/ab8742.jpg",
      "start_time": "2025-10-07T01:30:00.000Z"
    },
    "4632115": {
      "title": "Cinta Keluarga Pandya",
      "web_url": "782",
      "cover_url": "https://thumbor.prod.vidiocdn.com/TTfjuTjglT7a-HnhiISEZJUcVaU=/640x360/filters:strip_icc():quality(70)/vidio-media-production/uploads/livestreaming/schedule/thumbnail/4632115/ad027d.jpg",
      "start_time": "2025-10-07T06:30:00.000Z"
    },
    "4632116": {
      "title": "Zeynep",
      "web_url": "782",
      "cover_url": "https://thumbor.prod.vidiocdn.com/ETPG6rLzKscvQjlJn0HhpBvBO7I=/640x360/filters:strip_icc():quality(70)/vidio-media-production/uploads/livestreaming/schedule/thumbnail/4632116/70c02b.jpg",
      "start_time": "2025-10-07T08:00:00.000Z"
    },
    "4632117": {
      "title": "Takdir Cinta Layla",
      "web_url": "782",
      "cover_url": "https://thumbor.prod.vidiocdn.com/_uREalV_IwWMJ_Z-3N26nnvsm-o=/640x360/filters:strip_icc():quality(70)/vidio-media-production/uploads/livestreaming/schedule/thumbnail/4632117/8d71c5.jpg",
      "start_time": "2025-10-07T09:30:00.000Z"
    },
    "4632119": {
      "title": "Rindu Tak Berujung",
      "web_url": "782",
      "cover_url": "https://thumbor.prod.vidiocdn.com/HazuR_0KJ3EeIe83nP93XANysss=/640x360/filters:strip_icc():quality(70)/vidio-media-production/uploads/livestreaming/schedule/thumbnail/4632119/d476d0.jpg",
      "start_time": "2025-10-07T12:30:00.000Z"
    },
    "4632247": {
      "title": "Merangkai Kisah Indah",
      "web_url": "205",
      "cover_url": "https://thumbor.prod.vidiocdn.com/rOwEMb0UfSDFmaMWJoFrwe1EnOU=/640x360/filters:strip_icc():quality(70)/vidio-media-production/uploads/livestreaming/schedule/thumbnail/4632247/fe2545.jpg",
      "start_time": "2025-10-06T10:00:00.000Z"
    },
    "4632248": {
      "title": "D'Academy 7 - Top 13 Group 3 Result",
      "web_url": "205",
      "cover_url": "https://thumbor.prod.vidiocdn.com/u8LVQv5fhSKFhMRn22IavL3IFK4=/640x360/filters:strip_icc():quality(70)/vidio-media-production/uploads/livestreaming/schedule/thumbnail/4632248/f4099b.jpg",
      "start_time": "2025-10-06T12:00:00.000Z"
    },
    "4632249": {
      "title": "Mega Film Asia: Chasing The Dragon",
      "web_url": "205",
      "cover_url": "https://thumbor.prod.vidiocdn.com/1HA-NCCnZPrxb-Tbqx1oIAeIojM=/640x360/filters:strip_icc():quality(70)/vidio-media-production/uploads/livestreaming/schedule/thumbnail/4632249/6a1dc0.jpg",
      "start_time": "2025-10-06T16:30:00.000Z"
    },
    "4632250": {
      "title": "Super Sale Indonesia",
      "web_url": "204",
      "cover_url": "https://thumbor.prod.vidiocdn.com/k5IQ9VnfcgIR8qn6OCbFNNB63Q4=/640x360/filters:strip_icc():quality(70)/vidio-media-production/uploads/livestreaming/schedule/thumbnail/4632250/21333f.jpg",
      "start_time": "2025-10-06T05:30:00.000Z"
    },
    "4632254": {
      "title": "FTV Siang: Berdomba Domba Mengejar Cintamu",
      "web_url": "204",
      "cover_url": "https://thumbor.prod.vidiocdn.com/XVdwVpZtaRVK2rQ1az0NJT4IgTM=/640x360/filters:strip_icc():quality(70)/vidio-media-production/uploads/livestreaming/schedule/thumbnail/4632254/b3da12.jpg",
      "start_time": "2025-10-06T07:00:00.000Z"
    },
    "4632262": {
      "title": "American Ninja Warrior Junior Season 2",
      "web_url": "206",
      "cover_url": "https://thumbor.prod.vidiocdn.com/LOjuBmmCzdxPer03vgVVpRKlNvY=/640x360/filters:strip_icc():quality(70)/vidio-media-production/uploads/livestreaming/schedule/thumbnail/4632262/233038.jpg",
      "start_time": "2025-10-06T11:00:00.000Z"
    },
    "4632264": {
      "title": "Tabir Cerita",
      "web_url": "206",
      "cover_url": "https://thumbor.prod.vidiocdn.com/dKSbNEaraJR9BTVUbxBdOe7KzzA=/640x360/filters:strip_icc():quality(70)/vidio-media-production/uploads/livestreaming/schedule/thumbnail/4632264/4eb8d0.jpg",
      "start_time": "2025-10-06T12:00:00.000Z"
    },
    "4632734": {
      "title": "Liputan 6 Pagi Moji",
      "web_url": "206",
      "cover_url": "https://thumbor.prod.vidiocdn.com/FPiidgXUA0eTDs4WsFpPGpDQYD0=/640x360/filters:strip_icc():quality(70)/vidio-media-production/uploads/livestreaming/schedule/thumbnail/4632734/26ec5e.jpg",
      "start_time": "2025-10-06T23:15:00.000Z"
    },
    "4632760": {
      "title": "American Ninja Warrior Junior SEAson 2",
      "web_url": "206",
      "cover_url": "https://thumbor.prod.vidiocdn.com/TNaSv8IhhuAPjkulR04ZzDQxH2Y=/640x360/filters:strip_icc():quality(70)/vidio-media-production/uploads/livestreaming/schedule/thumbnail/4632760/cb0a2e.jpg",
      "start_time": "2025-10-07T11:00:00.000Z"
    },
    "4632762": {
      "title": "Tabir Cerita",
      "web_url": "206",
      "cover_url": "https://thumbor.prod.vidiocdn.com/-1UZkRoNs2JAx_mFqfi92RiBGPo=/640x360/filters:strip_icc():quality(70)/vidio-media-production/uploads/livestreaming/schedule/thumbnail/4632762/4fc78a.jpg",
      "start_time": "2025-10-07T13:00:00.000Z"
    },
    "4632791": {
      "title": "Mega Film Asia: Shaolin Temple",
      "web_url": "205",
      "cover_url": "https://thumbor.prod.vidiocdn.com/VQTEAqfvfYfInkPLDMBwUrK4c4U=/640x360/filters:strip_icc():quality(70)/vidio-media-production/uploads/livestreaming/schedule/thumbnail/4632791/4e2e81.jpg",
      "start_time": "2025-10-06T18:00:00.000Z"
    },
    "4632792": {
      "title": "Mega Film Asia: Black Mask",
      "web_url": "205",
      "cover_url": "https://thumbor.prod.vidiocdn.com/MAutYUpHK1iFZwObORuzrLVyRNw=/640x360/filters:strip_icc():quality(70)/vidio-media-production/uploads/livestreaming/schedule/thumbnail/4632792/140027.jpg",
      "start_time": "2025-10-06T20:00:00.000Z"
    },
    "4632793": {
      "title": "Mega Film Asia: Chinese Zodiac",
      "web_url": "205",
      "cover_url": "https://thumbor.prod.vidiocdn.com/FZNEGsOWwiWYklVS1p-CBQBOMSw=/640x360/filters:strip_icc():quality(70)/vidio-media-production/uploads/livestreaming/schedule/thumbnail/4632793/d8cf3a.jpg",
      "start_time": "2025-10-07T16:30:00.000Z"
    },
    "4632818": {
      "title": "Merangkai Kisah Indah",
      "web_url": "205",
      "cover_url": "https://thumbor.prod.vidiocdn.com/RhoLwIQut0w5ndXXhlOfqOHYeME=/640x360/filters:strip_icc():quality(70)/vidio-media-production/uploads/tv_program/thumbnail/389747/fc3ce1.jpg",
      "start_time": "2025-10-07T10:00:00.000Z"
    },
    "4632866": {
      "title": "D' Academy 7 - Top 13 Group 3 Result",
      "web_url": "205",
      "cover_url": "https://thumbor.prod.vidiocdn.com/QRiNbWl6TmOJJAmEA9CRIf3OeEE=/640x360/filters:strip_icc():quality(70)/vidio-media-production/uploads/livestreaming/schedule/thumbnail/4632866/cf2371.jpg",
      "start_time": "2025-10-07T12:00:00.000Z"
    },
    "4632896": {
      "title": "Liputan 6 Pagi",
      "web_url": "204",
      "cover_url": "https://thumbor.prod.vidiocdn.com/PpPDYfv88RPOR_G5XYCTux6sJBA=/640x360/filters:strip_icc():quality(70)/vidio-media-production/uploads/livestreaming/schedule/thumbnail/4632896/1508cd.jpg",
      "start_time": "2025-10-06T22:00:00.000Z"
    },
    "4632904": {
      "title": "Asmara Gen Z",
      "web_url": "204",
      "cover_url": "https://thumbor.prod.vidiocdn.com/Y_dgZwLOsingegbEPn6FsphcheA=/640x360/filters:strip_icc():quality(70)/vidio-media-production/uploads/tv_program/thumbnail/387307/cd8554.jpg",
      "start_time": "2025-10-07T00:00:00.000Z"
    },
    "4632905": {
      "title": "Asmara Gen Z",
      "web_url": "204",
      "cover_url": "https://thumbor.prod.vidiocdn.com/Y_dgZwLOsingegbEPn6FsphcheA=/640x360/filters:strip_icc():quality(70)/vidio-media-production/uploads/tv_program/thumbnail/387307/cd8554.jpg",
      "start_time": "2025-10-07T10:00:00.000Z"
    },
    "4632916": {
      "title": "FTV Pagi Spesial: Ceo Of Cewek Jagoan Komplek",
      "web_url": "204",
      "cover_url": "https://thumbor.prod.vidiocdn.com/tcjtb0wmi1pvO0r3JwOdCEzVLnE=/640x360/filters:strip_icc():quality(70)/vidio-media-production/uploads/livestreaming/schedule/thumbnail/4632916/d3e198.jpg",
      "start_time": "2025-10-07T01:30:00.000Z"
    },
    "4632917": {
      "title": "FTV Pagi: Ku Terpikat Sama Cewek Kemaling Sole",
      "web_url": "204",
      "cover_url": "https://thumbor.prod.vidiocdn.com/bwOmmEJb4q84NkReEGCNdszhohs=/640x360/filters:strip_icc():quality(70)/vidio-media-production/uploads/livestreaming/schedule/thumbnail/4632917/2077e1.jpg",
      "start_time": "2025-10-07T03:00:00.000Z"
    },
    "4632918": {
      "title": "Liputan 6 Siang",
      "web_url": "204",
      "cover_url": "https://thumbor.prod.vidiocdn.com/v6lgJqICLC7NKjkvXMdM3yHtkI4=/640x360/filters:strip_icc():quality(70)/vidio-media-production/uploads/livestreaming/schedule/thumbnail/4632918/849506.jpg",
      "start_time": "2025-10-07T05:00:00.000Z"
    },
    "4632924": {
      "title": "Super Sale Indonesia",
      "web_url": "204",
      "cover_url": "https://thumbor.prod.vidiocdn.com/6SO0_1OzgaBB6crQyRYzl8z93QY=/640x360/filters:strip_icc():quality(70)/vidio-media-production/uploads/livestreaming/schedule/thumbnail/4632924/a5be12.jpg",
      "start_time": "2025-10-07T05:30:00.000Z"
    },
    "4632928": {
      "title": "FTV Siang: Tak Habis Fikri Ditembak Cinta Supir",
      "web_url": "204",
      "cover_url": "https://thumbor.prod.vidiocdn.com/T822_Qo62icS6db63dFocVqc4NE=/640x360/filters:strip_icc():quality(70)/vidio-media-production/uploads/livestreaming/schedule/thumbnail/4632928/2cefcc.jpg",
      "start_time": "2025-10-07T07:00:00.000Z"
    },
    "4632929": {
      "title": "Azizah : Cinta 6 Hati",
      "web_url": "204",
      "cover_url": "https://thumbor.prod.vidiocdn.com/HmpQM9UMdqb4Q6P06Zus5Kl_diw=/640x360/filters:strip_icc():quality(70)/vidio-media-production/uploads/livestreaming/schedule/thumbnail/4632929/632536.jpg",
      "start_time": "2025-10-07T08:30:00.000Z"
    },
    "4632935": {
      "title": "Cinta Sedalam Rindu",
      "web_url": "204",
      "cover_url": "https://thumbor.prod.vidiocdn.com/sa_CEEMzU6PGyGxInw1tQi3VnO0=/640x360/filters:strip_icc():quality(70)/vidio-media-production/uploads/image/source/47271/251f72.png",
      "start_time": "2025-10-07T11:30:00.000Z"
    },
    "4632941": {
      "title": "Cinta Di Bawah Tangan",
      "web_url": "204",
      "cover_url": "https://thumbor.prod.vidiocdn.com/Xr8AAOVjClvDNr9P3fkGaB9Zn20=/640x360/filters:strip_icc():quality(70)/vidio-web-prod-livestreaming/uploads/livestreaming/image/204/sctv-5ef966.jpg",
      "start_time": "2025-10-07T13:15:00.000Z"
    },
    "4632947": {
      "title": "Wanita Istimewa",
      "web_url": "204",
      "cover_url": "https://thumbor.prod.vidiocdn.com/lf-jR4lNFe3YXucbsbO7epY1QW8=/640x360/filters:strip_icc():quality(70)/vidio-media-production/uploads/image/source/47544/a91f3d.jpg",
      "start_time": "2025-10-07T14:45:00.000Z"
    }
  },
  "headers": {
    "content-type": "application/json",
    "x-api-platform": "tv-android",
    "x-api-auth": "laZOmogezono5ogekaso5oz4Mezimew1",
    "x-user-token": "vMFo7JhB3sXprNaHVL3n",
    "x-visitor-id": "51b995d2-833d-4a3c-b021-952b647424cb",
    "x-api-app-info": "tv-android/10/2.45.11-736",
    "referer": "androidtv-app://com.vidio.android.tv",
    "hash": "YuZ4UAzQEeFxMjRS2ea9oxo40vsqKnuKtRAO2kJJ7Ji6MpxXgnMvZlF8JH8Yb0IBdCBqwDg9BHHX2ctVoa5WetrDbijRjUNg8Rql5p5dmlPZwhXsSyS3gZhXyLWHEYlANrH30K4swP8xdLcDZE9AmZ",
    "cookie": "country_id=ID; ahoy_visitor=aa3efdc4-e8cb-42ba-85ed-ea16ea518c0c; ahoy_visit=02068aae-41b9-4701-bfc3-5c36541c32c1; shva=1; _vidio=true; plenty_id=189401818; x_user_token=T58u_TyayBAXduZhS7mW; access_token=eyJhbGciOiJIUzI1NiJ9.eyJkYXRhIjp7InR5cGUiOiJhY2Nlc3NfdG9rZW4iLCJ1aWQiOjE4OTQwMTgxOH0sImV4cCI6MTc1OTgwOTYwM30.v5cRAuNnfGq5Gj9h1wZPEagJqEhvs-kiGGg4zt4WU6U; _vidio_session=OOgfwxCtKqYazdjvvoUNNFQHooVgyF4mo9J5H2g7fe5QAkxTwHPixMgL46mbkp6Mjp0CGrTDVQpF8GOAauBSM8mmsNzWNR3HUJUnkjPhlrx7%2FrXUaR9o0tLeiENfFXTWcTeX935O5ND5g8S6wfOYcRePPEUnaJ%2F4Ng6BEzEBNmZI6KbZp300lp%2BdjmjLm%2BCLhkHW9Dpw4TRlIrgga%2Blku9Nb%2BnS4UYn2wyr5Ju7hKE2iT%2FhHtcVsEvBBPvDWWFwdwP4am%2B0sfm%2FCIFb4dRPXlSwTRe1IFv3qO5YCRAf9DmvlsGO3AsvHDX2kXZ7qFaawR%2BSA6Yduc7%2FccgzrKJIwAXi%2F%2B6z6jeq7T5mMHQSwuiNNXqaqm6Y2k6L6re8AYhIj2M3tFAvzBP0u1nG9R%2BDBOAebn9GcfpXsGKl6CSTB2S65qDR0Ua8werE29BNAgMukpJiw20%2FHukAT0NtrqH5aaZ4xO8dhUr1GIPL%2BFGXLtmGv5NQS8wj%2BuRI%2FquFyLvHF6kywchHsErUMVECsdfH4ImxgiSXvljJZIwZ%2FfzVt024t6p7q2daam%2FkSaZbM5YLktZcu2CywhEsvmZWH9fGxTDJrl3%2FCRSCujm6jL9xAr%2B8JGorY491uLDaImdKA1FvaaSSIuw%2BPKZmhjZy0xeiHR3Vn0043PwsvnoHo66IE--U3MKEDIN8qSBKHeL--LlxjIMGprjHbeWaGH6XMjA%3D%3D",
    "accept": "*/*",
    "origin": "https://www.vidio.com",
    "user-agent": "tv-android/2.45.11 (736)",
    "x-api-key": "CH1ZFsN4N/MIfAds1DL9mP151CNqIpWHqZGRr+LkvUyiq3FRPuP1Kt6aK+pG3nEC1FXt0ZAAJ5FKP8QU8CZ5/vLkcEgAEXB4f6CT8Xt45xoHKcIOakutssomGDquaUE+l1kbIDUAoIB+GgYvHUUdjN7ymzJp0UBxFgxn08IWTgw=",
    "x-client": "1759723208.401",
    "x-secure-level": "2",
    "x-signature": "dd382e3961f3683cdbcc3b6a33b03c838bcb0a48684e341dcd9a1a42e2dfabf0",
    "x-user-email": "tcprksqc@gmail.com",
    "luws": "3B987859-B7F7-4834-6898-8F142C503DE5_189401818",
    "sec-ch-ua": "\"Not;A=Brand\";v=\"99\", \"HeadlessChrome\";v=\"139\", \"Chromium\";v=\"139\"",
    "sec-ch-ua-mobile": "?0",
    "sec-ch-ua-platform": "\"Windows\"",
    "205-dash": "https://etslive-v3-vidio-com-tokenized.akamaized.net/stream/205/file/stream.mpd?hdnts=exp=1759737612~acl=/stream/205/file/stream.mpd!/stream/205/file/*/aac/*!/stream/205/file/*/*-1080p/*!/stream/205/file/*/*-720p/*!/stream/205/file/*/*-480p/*!/stream/205/file/*/*-360p/*~id=189401818~hmac=df69cc04178b6d1119baa0c97487e46d756ca97ad97301f3451dfc986c1c2489",
    "205-hls": "https://etslive-v3-vidio-com-tokenized.akamaized.net/stream/205/file/master.m3u8?hdnts=exp=1759737612~acl=/stream/205/file/master.m3u8!/stream/205/file/*/aac/*!/stream/205/file/*/*-1080p/*!/stream/205/file/*/*-720p/*!/stream/205/file/*/*-480p/*!/stream/205/file/*/*-360p/*~id=189401818~hmac=c0ca45609f94b47ad7183762284f2189f25b48b9245f2105dfcef5dd655cf92f",
    "205-drm": null,
    "204-dash": "https://etslive-v3-vidio-com-tokenized.akamaized.net/stream/204/file/stream.mpd?hdnts=exp=1759737612~acl=/stream/204/file/stream.mpd!/stream/204/file/*/aac/*!/stream/204/file/*/*-1080p/*!/stream/204/file/*/*-720p/*!/stream/204/file/*/*-480p/*!/stream/204/file/*/*-360p/*~id=189401818~hmac=78e6588f834de576f9d019fde0a6a7ba65319481435b307301158fd3202b4930",
    "204-hls": "https://etslive-v3-vidio-com-tokenized.akamaized.net/stream/204/file/master.m3u8?hdnts=exp=1759737612~acl=/stream/204/file/master.m3u8!/stream/204/file/*/aac/*!/stream/204/file/*/*-1080p/*!/stream/204/file/*/*-720p/*!/stream/204/file/*/*-480p/*!/stream/204/file/*/*-360p/*~id=189401818~hmac=439a3582d3b6b8f1d4030ebab37709444b708ca772480cb2bf9165e3b6985c9f",
    "204-drm": null,
    "734-dash": "https://etslive-v3-vidio-com-tokenized.akamaized.net/stream/734/file/stream.mpd?hdnts=exp=1759737612~acl=/stream/734/file/stream.mpd!/stream/734/file/*/aac/*!/stream/734/file/*/*-1080p/*!/stream/734/file/*/*-720p/*!/stream/734/file/*/*-480p/*!/stream/734/file/*/*-360p/*~id=189401818~hmac=74f846b013f17ebf3cb8768b966be79bceb3bf30ffd3d140a0287c828d0b4355",
    "734-hls": "https://etslive-v3-vidio-com-tokenized.akamaized.net/stream/734/file/master.m3u8?hdnts=exp=1759737612~acl=/stream/734/file/master.m3u8!/stream/734/file/*/aac/*!/stream/734/file/*/*-1080p/*!/stream/734/file/*/*-720p/*!/stream/734/file/*/*-480p/*!/stream/734/file/*/*-360p/*~id=189401818~hmac=bb50832de9443a15eb2d3d04aed1cc66eaa909b3e08ee58571111e56576d0586",
    "734-drm": null,
    "206-dash": "https://etslive-v3-vidio-com-tokenized.akamaized.net/stream/206/file/stream.mpd?hdnts=exp=1759737612~acl=/stream/206/file/stream.mpd!/stream/206/file/*/aac/*!/stream/206/file/*/*-1080p/*!/stream/206/file/*/*-720p/*!/stream/206/file/*/*-480p/*!/stream/206/file/*/*-360p/*~id=189401818~hmac=ac329de12be8da37d303e09f3c011b2bf5038609b55c5d1ddd773ec92a65ae03",
    "206-hls": "https://etslive-v3-vidio-com-tokenized.akamaized.net/stream/206/file/master.m3u8?hdnts=exp=1759737612~acl=/stream/206/file/master.m3u8!/stream/206/file/*/aac/*!/stream/206/file/*/*-1080p/*!/stream/206/file/*/*-720p/*!/stream/206/file/*/*-480p/*!/stream/206/file/*/*-360p/*~id=189401818~hmac=f53e3bdaf5493c28b82d965737ff3309365164b120e4628f4d093cf565213726",
    "206-drm": null,
    "733-dash": "https://etslive-v3-vidio-com-tokenized.akamaized.net/stream/733/file/stream.mpd?hdnts=exp=1759737612~acl=/stream/733/file/stream.mpd!/stream/733/file/*/aac/*!/stream/733/file/*/*-1080p/*!/stream/733/file/*/*-720p/*!/stream/733/file/*/*-480p/*!/stream/733/file/*/*-360p/*~id=189401818~hmac=253d584c10ea00536f53a293a9026ac4913751928b184eb5b40a99fc19c96aab",
    "733-hls": "https://etslive-v3-vidio-com-tokenized.akamaized.net/stream/733/file/master.m3u8?hdnts=exp=1759737612~acl=/stream/733/file/master.m3u8!/stream/733/file/*/aac/*!/stream/733/file/*/*-1080p/*!/stream/733/file/*/*-720p/*!/stream/733/file/*/*-480p/*!/stream/733/file/*/*-360p/*~id=189401818~hmac=f71fcfd9779d6c2f9946220ce69689499e1c05c170bfd3ad93cd009b9b971d38",
    "733-drm": null,
    "18105-dash": "https://etslive-v3-vidio-com-tokenized.akamaized.net/stream/18105/file/stream.mpd?hdnts=exp=1759737612~acl=/stream/18105/file/stream.mpd!/stream/18105/file/*/aac/*!/stream/18105/file/*/*-1080p/*!/stream/18105/file/*/*-720p/*!/stream/18105/file/*/*-480p/*!/stream/18105/file/*/*-360p/*~id=189401818~hmac=84e27ae51764f34271ea9dc6492ecd20f1c15ca538f4d3f2beabd8fff24d879c",
    "18105-hls": "https://etslive-v3-vidio-com-tokenized.akamaized.net/stream/18105/file/master.m3u8?hdnts=exp=1759737612~acl=/stream/18105/file/master.m3u8!/stream/18105/file/*/aac/*!/stream/18105/file/*/*-1080p/*!/stream/18105/file/*/*-720p/*!/stream/18105/file/*/*-480p/*!/stream/18105/file/*/*-360p/*~id=189401818~hmac=b4f2240a17b0f0a791a83189ab370f5af730cf1546572f0d0aa9076f93c6c88a",
    "18105-drm": null,
    "all-sections": "17505-17875-18190-18249-18250-18252-19541-19542-19543-19548-19657-6317-6786",
    "all-vidiolivetv": []
  }
}