{
  "time": "2025-09-30T23:18:04.529Z",
  "sections": {
    "4606949": {
      "title": "ATP 500: China Open 2025 - Final",
      "web_url": "6317",
      "cover_url": "https://thumbor.prod.vidiocdn.com/xz5_0XP6b2TqEJYpjvkAjiSjVkQ=/640x360/filters:strip_icc():quality(70)/vidio-media-production/uploads/livestreaming/schedule/thumbnail/4606949/d878c7.jpg",
      "start_time": "2025-10-01T06:00:00.000Z"
    },
    "4606950": {
      "title": "Qarabag FK vs Copenhagen - UEFA Champions League",
      "web_url": "6317",
      "cover_url": "https://thumbor.prod.vidiocdn.com/SFjgpH1uAlg1WFPZWGg652d2AiQ=/640x360/filters:strip_icc():quality(70)/vidio-media-production/uploads/livestreaming/schedule/thumbnail/4606950/6f5f26.jpg",
      "start_time": "2025-10-01T16:40:00.000Z"
    },
    "4607557": {
      "title": "WTA 1000: China Open - Day 6",
      "web_url": "6786",
      "cover_url": "https://thumbor.prod.vidiocdn.com/MwLLfYENnJn9OXl9Fdu1XAysRcQ=/640x360/filters:strip_icc():quality(70)/vidio-media-production/uploads/livestreaming/schedule/thumbnail/4607557/b01518.jpg",
      "start_time": "2025-10-01T06:30:00.000Z"
    },
    "4607558": {
      "title": "WTA 1000: China Open - Day 6",
      "web_url": "6786",
      "cover_url": "https://thumbor.prod.vidiocdn.com/TFQ5SWhPe7JBgvxrtQEyed6im5M=/640x360/filters:strip_icc():quality(70)/vidio-media-production/uploads/livestreaming/schedule/thumbnail/4607558/7311e5.jpg",
      "start_time": "2025-10-01T11:00:00.000Z"
    },
    "4607559": {
      "title": "WTA 1000: China Open - Quarter Final",
      "web_url": "6786",
      "cover_url": "https://thumbor.prod.vidiocdn.com/CB84nSA7lZjngj-lE1tXUyYQVlA=/640x360/filters:strip_icc():quality(70)/vidio-media-production/uploads/livestreaming/schedule/thumbnail/4607559/a14ee5.jpg",
      "start_time": "2025-10-02T07:00:00.000Z"
    },
    "4607560": {
      "title": "WTA 1000: China Open - Quarter Final",
      "web_url": "6786",
      "cover_url": "https://thumbor.prod.vidiocdn.com/ufuF8s-iy3pu7WDdwW76xjrhGZQ=/640x360/filters:strip_icc():quality(70)/vidio-media-production/uploads/livestreaming/schedule/thumbnail/4607560/936a15.jpg",
      "start_time": "2025-10-02T10:00:00.000Z"
    },
    "4607561": {
      "title": "WTA 1000: China Open - Quarter Final",
      "web_url": "6786",
      "cover_url": "https://thumbor.prod.vidiocdn.com/ZNx2O0ffQBu8LW8npOWwKJ_Lhso=/640x360/filters:strip_icc():quality(70)/vidio-media-production/uploads/livestreaming/schedule/thumbnail/4607561/44da1d.jpg",
      "start_time": "2025-10-03T07:00:00.000Z"
    },
    "4607562": {
      "title": "WTA 1000: China Open - Quarter Final",
      "web_url": "6786",
      "cover_url": "https://thumbor.prod.vidiocdn.com/9PS72kRPBjqFS_zyUL2NTwp6kJ8=/640x360/filters:strip_icc():quality(70)/vidio-media-production/uploads/livestreaming/schedule/thumbnail/4607562/6f0086.jpg",
      "start_time": "2025-10-03T10:00:00.000Z"
    },
    "4607563": {
      "title": "Union Saint-Gilloise vs Newcastle - UEFA Champions League",
      "web_url": "6299",
      "cover_url": "https://thumbor.prod.vidiocdn.com/2P6cAGt2PDT0qR_0GDZZwU5VIPw=/640x360/filters:strip_icc():quality(70)/vidio-media-production/uploads/livestreaming/schedule/thumbnail/4607563/afd030.jpg",
      "start_time": "2025-10-01T16:40:00.000Z"
    },
    "4607565": {
      "title": "LOTTE Championship presented by Hoakalei - Round 1",
      "web_url": "18190",
      "cover_url": "https://thumbor.prod.vidiocdn.com/X1f7hGQwCCHt4AMGFS9ONzPQ_IE=/640x360/filters:strip_icc():quality(70)/vidio-media-production/uploads/livestreaming/schedule/thumbnail/4607565/bfffb2.jpg",
      "start_time": "2025-10-01T23:00:00.000Z"
    },
    "4607566": {
      "title": "LOTTE Championship presented by Hoakalei - Round 2",
      "web_url": "18190",
      "cover_url": "https://thumbor.prod.vidiocdn.com/Rs_cMI_2pyVsCVNMC-X1OKeklyc=/640x360/filters:strip_icc():quality(70)/vidio-media-production/uploads/livestreaming/schedule/thumbnail/4607566/a2017d.jpg",
      "start_time": "2025-10-02T23:00:00.000Z"
    },
    "4607567": {
      "title": "LOTTE Championship presented by Hoakalei - Round 3",
      "web_url": "18190",
      "cover_url": "https://thumbor.prod.vidiocdn.com/5lKovnsfeBe8C-IEebKZ0kQS5vc=/640x360/filters:strip_icc():quality(70)/vidio-media-production/uploads/livestreaming/schedule/thumbnail/4607567/d2a347.jpg",
      "start_time": "2025-10-03T23:00:00.000Z"
    },
    "4607568": {
      "title": "LOTTE Championship presented by Hoakalei - Final Round",
      "web_url": "18190",
      "cover_url": "https://thumbor.prod.vidiocdn.com/30YE93Qiig78wUaiJZtNYsOWpR4=/640x360/filters:strip_icc():quality(70)/vidio-media-production/uploads/livestreaming/schedule/thumbnail/4607568/b20fac.jpg",
      "start_time": "2025-10-04T23:00:00.000Z"
    },
    "4607910": {
      "title": "Barcelona vs PSG - UEFA Champions League",
      "web_url": "6299",
      "cover_url": "https://thumbor.prod.vidiocdn.com/oUeQ5VuDYxux_-3x8s63hrEzT24=/640x360/filters:strip_icc():quality(70)/vidio-media-production/uploads/livestreaming/schedule/thumbnail/4607910/713e6b.jpg",
      "start_time": "2025-10-01T18:55:00.000Z"
    },
    "4607911": {
      "title": "Monaco vs Man City - UEFA Champions League",
      "web_url": "6317",
      "cover_url": "https://thumbor.prod.vidiocdn.com/YYxIL4-R4vgFEsYi4-uQeiujpZU=/640x360/filters:strip_icc():quality(70)/vidio-media-production/uploads/livestreaming/schedule/thumbnail/4607911/e9d840.jpg",
      "start_time": "2025-10-01T18:55:00.000Z"
    },
    "4607915": {
      "title": "Arsenal vs Olympiacos - UEFA Champions League",
      "web_url": "17883",
      "cover_url": "https://thumbor.prod.vidiocdn.com/slfGGZF8jI0XC4sv-4SwS3YmSC0=/640x360/filters:strip_icc():quality(70)/vidio-media-production/uploads/livestreaming/schedule/thumbnail/4607915/c1c90d.jpg",
      "start_time": "2025-10-01T18:30:00.000Z"
    },
    "4610342": {
      "title": "Dortmund vs Athletic Club - UEFA Champions League",
      "web_url": "18302",
      "cover_url": "https://thumbor.prod.vidiocdn.com/IUFvAmN5BpwyPytiM8WY6mPXzmM=/640x360/filters:strip_icc():quality(70)/vidio-media-production/uploads/livestreaming/schedule/thumbnail/4610342/5bbfe8.jpg",
      "start_time": "2025-10-01T18:50:00.000Z"
    },
    "4610715": {
      "title": "Leverkusen vs PSV - UEFA Champions League",
      "web_url": "18305",
      "cover_url": "https://thumbor.prod.vidiocdn.com/TYw0BSJg-bISkv9MrNhQ3dHOuvo=/640x360/filters:strip_icc():quality(70)/vidio-media-production/uploads/livestreaming/schedule/thumbnail/4610715/63c747.jpg",
      "start_time": "2025-10-01T18:50:00.000Z"
    },
    "4610716": {
      "title": "Napoli vs Sporting - UEFA Champions League",
      "web_url": "18304",
      "cover_url": "https://thumbor.prod.vidiocdn.com/WDlVevZl_FE77kMzX7n_LA8-eck=/640x360/filters:strip_icc():quality(70)/vidio-media-production/uploads/livestreaming/schedule/thumbnail/4610716/d84928.jpg",
      "start_time": "2025-10-01T18:50:00.000Z"
    },
    "4610719": {
      "title": "Villarreal vs Juventus - UEFA Champions League",
      "web_url": "18303",
      "cover_url": "https://thumbor.prod.vidiocdn.com/B_qpducQLMyhZ1DmsT96eovOoGA=/640x360/filters:strip_icc():quality(70)/vidio-media-production/uploads/livestreaming/schedule/thumbnail/4610719/1f3322.jpg",
      "start_time": "2025-10-01T18:50:00.000Z"
    },
    "4610724": {
      "title": "Roma vs LOSC - UEFA Europa League",
      "web_url": "19603",
      "cover_url": "https://thumbor.prod.vidiocdn.com/QEMLlMDjVdUFKRRpup6O8NLC3BQ=/640x360/filters:strip_icc():quality(70)/vidio-media-production/uploads/livestreaming/schedule/thumbnail/4610724/f3bee3.jpg",
      "start_time": "2025-10-02T16:15:00.000Z"
    },
    "4610725": {
      "title": "Brann vs Utrecht - UEFA Europa League",
      "web_url": "19601",
      "cover_url": "https://thumbor.prod.vidiocdn.com/_ukcQ4T44ODc_g2EnpFBOKhs1SU=/640x360/filters:strip_icc():quality(70)/vidio-media-production/uploads/livestreaming/schedule/thumbnail/4610725/8d70d6.jpg",
      "start_time": "2025-10-02T16:35:00.000Z"
    },
    "4610726": {
      "title": "Celtic vs Braga - UEFA Europa League",
      "web_url": "19602",
      "cover_url": "https://thumbor.prod.vidiocdn.com/6buB4Cu6kfwqQQYkQ_nJPLYv2CM=/640x360/filters:strip_icc():quality(70)/vidio-media-production/uploads/livestreaming/schedule/thumbnail/4610726/979a51.jpg",
      "start_time": "2025-10-02T16:35:00.000Z"
    },
    "4610728": {
      "title": "Fenerbahce vs Nice - UEFA Europa League",
      "web_url": "19599",
      "cover_url": "https://thumbor.prod.vidiocdn.com/3JsLy5i80AQkO5OEgJCef07B4_Y=/640x360/filters:strip_icc():quality(70)/vidio-media-production/uploads/livestreaming/schedule/thumbnail/4610728/5c419c.jpg",
      "start_time": "2025-10-02T16:35:00.000Z"
    },
    "4610730": {
      "title": "Ludogorets vs Real Betis - UEFA Europa League",
      "web_url": "19600",
      "cover_url": "https://thumbor.prod.vidiocdn.com/SVc1o48uBhxVKscxZlz_QxrRKbk=/640x360/filters:strip_icc():quality(70)/vidio-media-production/uploads/livestreaming/schedule/thumbnail/4610730/8deb98.jpg",
      "start_time": "2025-10-02T16:35:00.000Z"
    },
    "4610732": {
      "title": "FCSB vs Young Boys - UEFA Europa League",
      "web_url": "19629",
      "cover_url": "https://thumbor.prod.vidiocdn.com/P9Ezt4XBPA6t02zSzvyUuTPnnaU=/640x360/filters:strip_icc():quality(70)/vidio-media-production/uploads/livestreaming/schedule/thumbnail/4610732/7f467d.jpg",
      "start_time": "2025-10-02T16:35:00.000Z"
    },
    "4610734": {
      "title": "Panathinaikos vs Go Ahead Eagles - UEFA Europa League",
      "web_url": "19630",
      "cover_url": "https://thumbor.prod.vidiocdn.com/5sTjCGxOlcIN4UwLPnyI_VaifzQ=/640x360/filters:strip_icc():quality(70)/vidio-media-production/uploads/livestreaming/schedule/thumbnail/4610734/c2a489.jpg",
      "start_time": "2025-10-02T16:35:00.000Z"
    },
    "4610736": {
      "title": "Viktoria Plzen vs Malmo - UEFA Europa League",
      "web_url": "19631",
      "cover_url": "https://thumbor.prod.vidiocdn.com/01XESzASw_CXH4yv__yPbHVaXKM=/640x360/filters:strip_icc():quality(70)/vidio-media-production/uploads/livestreaming/schedule/thumbnail/4610736/37675d.jpg",
      "start_time": "2025-10-02T16:35:00.000Z"
    },
    "4612075": {
      "title": "ATP 1000: Rolex Shanghai Masters 2025 - Day 1",
      "web_url": "17875",
      "cover_url": "https://thumbor.prod.vidiocdn.com/5lQCgwVPZGP8ZHozgeuHP3dSdO8=/640x360/filters:strip_icc():quality(70)/vidio-media-production/uploads/livestreaming/schedule/thumbnail/4612075/147824.jpg",
      "start_time": "2025-10-01T04:30:00.000Z"
    },
    "4613303": {
      "title": "Leverkusen vs PSV - UEFA Youth League",
      "web_url": "6299",
      "cover_url": "https://thumbor.prod.vidiocdn.com/cMzJ3ff5K2J1T2KVIftM7LfOCXY=/640x360/filters:strip_icc():quality(70)/vidio-media-production/uploads/livestreaming/schedule/thumbnail/4613303/c2341a.jpg",
      "start_time": "2025-10-01T12:00:00.000Z"
    },
    "4613304": {
      "title": "Barcelona vs PSG - UEFA Youth League",
      "web_url": "6299",
      "cover_url": "https://thumbor.prod.vidiocdn.com/CJLOPkvITYzlCxwIKeA6rfk_KJ8=/640x360/filters:strip_icc():quality(70)/vidio-media-production/uploads/livestreaming/schedule/thumbnail/4613304/fdcfb5.jpg",
      "start_time": "2025-10-01T14:00:00.000Z"
    },
    "4613305": {
      "title": "Feyenoord vs Aston Villa - UEFA Europa League",
      "web_url": "6299",
      "cover_url": "https://thumbor.prod.vidiocdn.com/nrdUfZRtCqGShp42z_M62AgAdXo=/640x360/filters:strip_icc():quality(70)/vidio-media-production/uploads/livestreaming/schedule/thumbnail/4613305/933106.jpg",
      "start_time": "2025-10-02T19:00:00.000Z"
    },
    "4613306": {
      "title": "BDMNTN XL 2025 - Day 1 Session 1",
      "web_url": "17139",
      "cover_url": "https://thumbor.prod.vidiocdn.com/XAbl8HKnwDQ2xSNrgw-N__dkiWM=/640x360/filters:strip_icc():quality(70)/vidio-media-production/uploads/livestreaming/schedule/thumbnail/4613306/a750d2.jpg",
      "start_time": "2025-10-02T07:30:00.000Z"
    },
    "4613307": {
      "title": "ATP 1000: Rolex Shanghai Masters 2025 - Day 2",
      "web_url": "17875",
      "cover_url": "https://thumbor.prod.vidiocdn.com/ptCYfccigw6T_DyI6Zx3LYvBeXA=/640x360/filters:strip_icc():quality(70)/vidio-media-production/uploads/livestreaming/schedule/thumbnail/4613307/bc5be8.jpg",
      "start_time": "2025-10-02T04:30:00.000Z"
    },
    "4613308": {
      "title": "BDMNTN XL 2025 - Day 1 Session 2",
      "web_url": "17139",
      "cover_url": "https://thumbor.prod.vidiocdn.com/rEEPMU0OOsTW2zVIoRxf139qM6o=/640x360/filters:strip_icc():quality(70)/vidio-media-production/uploads/livestreaming/schedule/thumbnail/4613308/4afc5f.jpg",
      "start_time": "2025-10-02T12:00:00.000Z"
    },
    "4613309": {
      "title": "Bologna vs SC Freiburg - UEFA Europa League",
      "web_url": "17875",
      "cover_url": "https://thumbor.prod.vidiocdn.com/RGTB6dZdklETpekui6twQqgfXt0=/640x360/filters:strip_icc():quality(70)/vidio-media-production/uploads/livestreaming/schedule/thumbnail/4613309/07a03a.jpg",
      "start_time": "2025-10-02T16:45:00.000Z"
    },
    "4613310": {
      "title": "Rajadamnern 2025 Female Bantamweight Title",
      "web_url": "19388",
      "cover_url": "https://thumbor.prod.vidiocdn.com/SaoHfeBu2_D0b4QIjF204L0Q9us=/640x360/filters:strip_icc():quality(70)/vidio-media-production/uploads/livestreaming/schedule/thumbnail/4613310/17359d.jpg",
      "start_time": "2025-10-04T12:00:00.000Z"
    },
    "4613311": {
      "title": "Nottingham Forest vs Midtjylland - UEFA Europa League",
      "web_url": "6317",
      "cover_url": "https://thumbor.prod.vidiocdn.com/Jspt_qYUEOu8AVUk2Q-M0GijxD0=/640x360/filters:strip_icc():quality(70)/vidio-media-production/uploads/livestreaming/schedule/thumbnail/4613311/03c84d.jpg",
      "start_time": "2025-10-02T19:00:00.000Z"
    }
  },
  "vidioliveothers": {
    "17884": {
      "title": "Formula 1",
      "web_url": "17884",
      "cover_url": "https://thumbor.prod.vidiocdn.com/Rc1pHYZnd8l_siMi118TkKusbPM=/640x360/filters:strip_icc():quality(70)/vidio-web-prod-livestreaming/uploads/livestreaming/image/17884/formula-1-5ee872.jpg",
      "start_time": "2025-04-02T13:25:00.000Z"
    },
    "17939": {
      "title": "Serie A",
      "web_url": "17939",
      "cover_url": "https://thumbor.prod.vidiocdn.com/wXHWlA-BoQngb7zXvZBBr_GTWUA=/640x360/filters:strip_icc():quality(70)/vidio-web-prod-livestreaming/uploads/livestreaming/image/17939/serie-a-cc1557.jpg",
      "start_time": "2025-09-14T12:45:00.000Z"
    },
    "19404": {
      "title": "Sassuolo vs Udinese - Serie A",
      "web_url": "19404",
      "cover_url": "https://thumbor.prod.vidiocdn.com/L75r8v7GTx-FEErmxGLs3iXfnRM=/640x360/filters:strip_icc():quality(70)/vidio-web-prod-livestreaming/uploads/livestreaming/image/19404/serie-a-78c93e.jpg",
      "start_time": "2025-08-18T08:00:00.000Z"
    },
    "19636": {
      "title": "Presiden Prabowo Pimpin Upacara Peringatan Hari Kesaktian Pancasila",
      "web_url": "19636",
      "cover_url": "https://thumbor.prod.vidiocdn.com/vLBGsYxEU_IWla8feBINWqVhkPE=/640x360/filters:strip_icc():quality(70)/vidio-web-prod-livestreaming/uploads/livestreaming/image/19636/liputan-6-sctv-93ba81.jpg",
      "start_time": "2025-09-30T23:00:00.000Z"
    }
  },
  "headers": {
    "content-type": "application/json",
    "x-api-platform": "tv-android",
    "x-api-auth": "laZOmogezono5ogekaso5oz4Mezimew1",
    "x-user-token": "vMFo7JhB3sXprNaHVL3n",
    "x-visitor-id": "51b995d2-833d-4a3c-b021-952b647424cb",
    "x-api-app-info": "tv-android/10/2.45.11-736",
    "referer": "androidtv-app://com.vidio.android.tv",
    "hash": "BuLsY7BhCjID9OwLsB3wiDh9k3wf2Kzd5Qw2IuEYkHnVz0Hf8ne6fFx5JImzczqbuyEqZLWGeebdH4H80DikEr3TFeFKODqK35LaKtMMpkUL3WVLb2cZngXwfypAjlzK2lIp0nUVrBgczkwEuulRjM",
    "cookie": "country_id=ID; ahoy_visitor=39362326-efb7-4ddc-9adb-e73af9c5f31a; ahoy_visit=2037db8d-c14d-4485-997f-47584862652b; shva=1; _vidio=true; plenty_id=190210651; x_user_token=4QteoPUUHi-SEJuXERsw; access_token=eyJhbGciOiJIUzI1NiJ9.eyJkYXRhIjp7InR5cGUiOiJhY2Nlc3NfdG9rZW4iLCJ1aWQiOjE5MDIxMDY1MX0sImV4cCI6MTc1OTM2MDY4Nn0.SUawUU8Ye20ZPAw83bVdx7l_JJLn-gcOdCxcdkg_ORQ; _vidio_session=RePnaurihNYC9FHosF81ZFtmIiSRjME3vi8c%2F%2FKMp7toYOIkyJW7gRm3TShzfdS%2BwzDrqBhPPeBf%2FuHf8FIpTFfxUFxR7jjQkx%2B5CL8t9yJmhaXFdjpto63Yx%2BPi%2Flkd1zkGZysH35NDokqVH%2ByRLf6syfYxwCF400nY7xSscIt4FvYx0hQYHVcwDNqQoCDszPErmqRxoMJi2RDyIedx7ta9fFMVjTGpUffuO8BteF97sH0myCnBofCJ9bvXzMITCKzoEvZW4F%2FuiEZcLRznJ8E66FrU4UAoxbACzuB8VEq3wEYqTc4jNguy0hHEvRVEwz7uC2eNxjWUVP78WCsNkbcnr9tdpp%2FHJrUP17Yscf4F%2BvUPp8ONpdcqcM6khfYAcqa1PZnWn70XXjgSjVd%2BZsaGbgCwrDq7VjufMI96w7OlMhWazlsgx%2BUQH%2FT1gMzUuQzViOsb7j8%2BB5du9Stoi%2FekuL%2BOPZZcApNB5yLMv5Se%2FRiWhHFLfdyNjQNYTgAR%2FQbtq%2F8%2FIrYmGA%2BBE5w6xyMSPjDQFgnhEMCM4bPRNPOD3dZCFNW5kzLFlUli%2Bq%2Bj2FL1ztiwsGBsxobRwobBpOrTGkniptDTswmU5FApGgVIwFte4UdM04WtbnxJYXAk2MqDyjWvs2AybDWN06K2SGoCYHkyWpdTiobBTP8h--C%2FVNgK8kaYBWvdnb--4qaCD%2FxsSoKTyiaOW5jKug%3D%3D",
    "accept": "*/*",
    "origin": "https://www.vidio.com",
    "user-agent": "tv-android/2.45.11 (736)",
    "x-api-key": "CH1ZFsN4N/MIfAds1DL9mP151CNqIpWHqZGRr+LkvUyiq3FRPuP1Kt6aK+pG3nEC1FXt0ZAAJ5FKP8QU8CZ5/uS4O62/bCNuwAeKsQrDlGICH7GoxvoxjRo99fX1EyrU42CEQmQooc1a8wr3C6TJLfIye4CXBY0zvZcDmfUm3rM=",
    "x-client": "1759274292.802",
    "x-secure-level": "2",
    "x-signature": "1de5876440de2dd767f277f304ad9dd34326ca59b80bc80ce4b74ec043029ce5",
    "x-user-email": "stbpnwdi@gmail.com",
    "luws": "C79C0C03-21A0-DBB9-919A-74B24575D574_190210651",
    "sec-ch-ua": "\"Not;A=Brand\";v=\"99\", \"HeadlessChrome\";v=\"139\", \"Chromium\";v=\"139\"",
    "sec-ch-ua-mobile": "?0",
    "sec-ch-ua-platform": "\"Windows\"",
    "734-dash": "https://etslive-v3-vidio-com-tokenized.akamaized.net/stream/734/file/stream.mpd?hdnts=exp=1759288694~acl=/stream/734/file/stream.mpd!/stream/734/file/*/aac/*!/stream/734/file/*/*-1080p/*!/stream/734/file/*/*-720p/*!/stream/734/file/*/*-480p/*!/stream/734/file/*/*-360p/*~id=190210651~hmac=843896fa076bb63e230144f2199e605194d3f6ee832bdc8d936b38bb023d911a",
    "734-hls": "https://etslive-v3-vidio-com-tokenized.akamaized.net/stream/734/file/master.m3u8?hdnts=exp=1759288694~acl=/stream/734/file/master.m3u8!/stream/734/file/*/aac/*!/stream/734/file/*/*-1080p/*!/stream/734/file/*/*-720p/*!/stream/734/file/*/*-480p/*!/stream/734/file/*/*-360p/*~id=190210651~hmac=381f09ab2a5b2638f7dd6bc625532147c3a070d6f2453df910db2786ebe84d4d",
    "734-drm": null,
    "205-dash": "https://etslive-v3-vidio-com-tokenized.akamaized.net/stream/205/file/stream.mpd?hdnts=exp=1759288694~acl=/stream/205/file/stream.mpd!/stream/205/file/*/aac/*!/stream/205/file/*/*-1080p/*!/stream/205/file/*/*-720p/*!/stream/205/file/*/*-480p/*!/stream/205/file/*/*-360p/*~id=190210651~hmac=f617936d5aa5b64fb882482ade017b14912df9778a49e007e984622354f83663",
    "205-hls": "https://etslive-v3-vidio-com-tokenized.akamaized.net/stream/205/file/master.m3u8?hdnts=exp=1759288694~acl=/stream/205/file/master.m3u8!/stream/205/file/*/aac/*!/stream/205/file/*/*-1080p/*!/stream/205/file/*/*-720p/*!/stream/205/file/*/*-480p/*!/stream/205/file/*/*-360p/*~id=190210651~hmac=dc3999e20040e809a1cb3c4f04f80b13f862836d2cf4c285cd1415d6f10b5c1c",
    "205-drm": null,
    "204-dash": "https://etslive-v3-vidio-com-tokenized.akamaized.net/stream/204/file/stream.mpd?hdnts=exp=1759288694~acl=/stream/204/file/stream.mpd!/stream/204/file/*/aac/*!/stream/204/file/*/*-1080p/*!/stream/204/file/*/*-720p/*!/stream/204/file/*/*-480p/*!/stream/204/file/*/*-360p/*~id=190210651~hmac=d44b0387b404c981bd5b9053fd21b712680d31c17b5c05becd7a0e0bd8cd4b4f",
    "204-hls": "https://etslive-v3-vidio-com-tokenized.akamaized.net/stream/204/file/master.m3u8?hdnts=exp=1759288694~acl=/stream/204/file/master.m3u8!/stream/204/file/*/aac/*!/stream/204/file/*/*-1080p/*!/stream/204/file/*/*-720p/*!/stream/204/file/*/*-480p/*!/stream/204/file/*/*-360p/*~id=190210651~hmac=3b0891fedc5c541ffa9229ab610be6f5cb0f27af731653466247b04dde1aae7f",
    "204-drm": null,
    "18105-dash": "https://etslive-v3-vidio-com-tokenized.akamaized.net/stream/18105/file/stream.mpd?hdnts=exp=1759288694~acl=/stream/18105/file/stream.mpd!/stream/18105/file/*/aac/*!/stream/18105/file/*/*-1080p/*!/stream/18105/file/*/*-720p/*!/stream/18105/file/*/*-480p/*!/stream/18105/file/*/*-360p/*~id=190210651~hmac=ae9e72593bdf2a34003faf2faa792e831003c7b8aaaee55ceddc54cab96c07a3",
    "18105-hls": "https://etslive-v3-vidio-com-tokenized.akamaized.net/stream/18105/file/master.m3u8?hdnts=exp=1759288694~acl=/stream/18105/file/master.m3u8!/stream/18105/file/*/aac/*!/stream/18105/file/*/*-1080p/*!/stream/18105/file/*/*-720p/*!/stream/18105/file/*/*-480p/*!/stream/18105/file/*/*-360p/*~id=190210651~hmac=4fcf9931e6676ecb1a5540c19d0efa104d856937f3a36af843a85b522401f250",
    "18105-drm": null,
    "733-dash": "https://etslive-v3-vidio-com-tokenized.akamaized.net/stream/733/file/stream.mpd?hdnts=exp=1759288694~acl=/stream/733/file/stream.mpd!/stream/733/file/*/aac/*!/stream/733/file/*/*-1080p/*!/stream/733/file/*/*-720p/*!/stream/733/file/*/*-480p/*!/stream/733/file/*/*-360p/*~id=190210651~hmac=a1ca9ee25aa297d5a8c04ed932b5a4a129ab87457ec661afbf48bb11fa89f07e",
    "733-hls": "https://etslive-v3-vidio-com-tokenized.akamaized.net/stream/733/file/master.m3u8?hdnts=exp=1759288694~acl=/stream/733/file/master.m3u8!/stream/733/file/*/aac/*!/stream/733/file/*/*-1080p/*!/stream/733/file/*/*-720p/*!/stream/733/file/*/*-480p/*!/stream/733/file/*/*-360p/*~id=190210651~hmac=16b752a3ae00d7c707e2762054a07e117e4502fc38782fa9eaf84b9db9d7944b",
    "733-drm": null,
    "206-dash": "https://etslive-v3-vidio-com-tokenized.akamaized.net/stream/206/file/stream.mpd?hdnts=exp=1759288694~acl=/stream/206/file/stream.mpd!/stream/206/file/*/aac/*!/stream/206/file/*/*-1080p/*!/stream/206/file/*/*-720p/*!/stream/206/file/*/*-480p/*!/stream/206/file/*/*-360p/*~id=190210651~hmac=4e28656c0b30eef511cae6e3b9bf4ce71ba3702936bf0e9f5bc488801193fbef",
    "206-hls": "https://etslive-v3-vidio-com-tokenized.akamaized.net/stream/206/file/master.m3u8?hdnts=exp=1759288694~acl=/stream/206/file/master.m3u8!/stream/206/file/*/aac/*!/stream/206/file/*/*-1080p/*!/stream/206/file/*/*-720p/*!/stream/206/file/*/*-480p/*!/stream/206/file/*/*-360p/*~id=190210651~hmac=aa518c602b3ef975141c22850755e205852ff58deb883c87e3bf3451257299f7",
    "206-drm": null,
    "all-sections": "17139-17875-17883-18190-18302-18303-18304-18305-19388-19599-19600-19601-19602-19603-19629-19630-19631-6299-6317-6786",
    "all-vidiolivetv": [
      {
        "content_id": "205",
        "nama_channel": "Indosiar",
        "cover_url": "https://thumbor.prod.vidiocdn.com/0plBZ7Gso7gNBJxid9ksA8HMGxc=/230x230/filters:quality(70)/vidio-web-prod-livestreaming/uploads/livestreaming/square_image/205/54ab19.png"
      },
      {
        "content_id": "204",
        "nama_channel": "SCTV",
        "cover_url": "https://thumbor.prod.vidiocdn.com/kH-K9J4cROqL0TZrAyQhw7P5pBk=/230x230/filters:quality(70)/vidio-web-prod-livestreaming/uploads/livestreaming/square_image/204/4e9f5c.png"
      },
      {
        "content_id": "733",
        "nama_channel": "TRANS TV",
        "cover_url": "https://thumbor.prod.vidiocdn.com/__j35q7LPpcS2EgkR7v8GpE4USQ=/230x230/filters:quality(70)/vidio-web-prod-livestreaming/uploads/livestreaming/square_image/733/ecaa60.png"
      },
      {
        "content_id": "783",
        "nama_channel": "TVOne",
        "cover_url": "https://thumbor.prod.vidiocdn.com/APQ6a9vXvN6lU1zjeyL15IV_AJQ=/230x230/filters:quality(70)/vidio-web-prod-livestreaming/uploads/livestreaming/square_image/783/07750c.png"
      },
      {
        "content_id": "734",
        "nama_channel": "Trans7",
        "cover_url": "https://thumbor.prod.vidiocdn.com/-MEB2a6J4sB6SvBDimCb7JYP6WY=/230x230/filters:quality(70)/vidio-web-prod-livestreaming/uploads/livestreaming/square_image/734/131514.png"
      },
      {
        "content_id": "782",
        "nama_channel": "ANTV",
        "cover_url": "https://thumbor.prod.vidiocdn.com/IRVkD3QGRzroJ4IZzXBpS-0MRls=/230x230/filters:quality(70)/vidio-web-prod-livestreaming/uploads/livestreaming/square_image/782/e1af8b.png"
      },
      {
        "content_id": "206",
        "nama_channel": "Moji",
        "cover_url": "https://thumbor.prod.vidiocdn.com/g7gTjD2Il1GI4DJULOZ1cv6NSj4=/230x230/filters:quality(70)/vidio-web-prod-livestreaming/uploads/livestreaming/square_image/206/1823dc.png"
      },
      {
        "content_id": "777",
        "nama_channel": "Metro TV",
        "cover_url": "https://thumbor.prod.vidiocdn.com/u0aa_S_rQeujrp5eR6LwXdertrI=/230x230/filters:quality(70)/vidio-web-prod-livestreaming/uploads/livestreaming/square_image/777/ea8483.png"
      },
      {
        "content_id": "874",
        "nama_channel": "Kompas TV",
        "cover_url": "https://thumbor.prod.vidiocdn.com/Pf8yLSfHEUZeRI9tUzLDR2U8Zow=/230x230/filters:quality(70)/vidio-web-prod-livestreaming/uploads/livestreaming/square_image/874/042ca3.png"
      },
      {
        "content_id": "1561",
        "nama_channel": "RTV",
        "cover_url": "https://thumbor.prod.vidiocdn.com/cStgoV5oqj2Om_6NMOzK0AFY-sg=/230x230/filters:quality(70)/vidio-web-prod-livestreaming/uploads/livestreaming/square_image/1561/665aea.png"
      },
      {
        "content_id": "875",
        "nama_channel": "MDTV",
        "cover_url": "https://thumbor.prod.vidiocdn.com/LCZH_yEBnTYEQzrU1pB7w7ev-Bw=/230x230/filters:quality(70)/vidio-web-prod-livestreaming/uploads/livestreaming/square_image/875/325605.png"
      },
      {
        "content_id": "8237",
        "nama_channel": "Mentari TV",
        "cover_url": "https://thumbor.prod.vidiocdn.com/59CZO-IVdps6hUK6gEQqn-w-bCw=/230x230/filters:quality(70)/vidio-web-prod-livestreaming/uploads/livestreaming/square_image/8237/18585d.png"
      },
      {
        "content_id": "6441",
        "nama_channel": "TVRI",
        "cover_url": "https://thumbor.prod.vidiocdn.com/F6W__Y0wn_7mFW0cOuz7mi7qjWU=/230x230/filters:quality(70)/vidio-web-prod-livestreaming/uploads/livestreaming/square_image/6441/528cc9.png"
      },
      {
        "content_id": "6165",
        "nama_channel": "BTV",
        "cover_url": "https://thumbor.prod.vidiocdn.com/DoRk_b8tcmbwDHroNxP2-o6QRKU=/230x230/filters:quality(70)/vidio-web-prod-livestreaming/uploads/livestreaming/square_image/6165/8c950f.png"
      },
      {
        "content_id": "18280",
        "nama_channel": "Berita Satu",
        "cover_url": "https://thumbor.prod.vidiocdn.com/cSyueV9bIgkdLkvVWqIZOlR6TFQ=/230x230/filters:quality(70)/vidio-web-prod-livestreaming/uploads/livestreaming/square_image/18280/c7fc8f.png"
      },
      {
        "content_id": "18162",
        "nama_channel": "Garuda TV",
        "cover_url": "https://thumbor.prod.vidiocdn.com/qtIYvE-mjwMPwd-VUxilo2gFiAI=/230x230/filters:quality(70)/vidio-web-prod-livestreaming/uploads/livestreaming/square_image/18162/b4bea2.png"
      },
      {
        "content_id": "5415",
        "nama_channel": "Jaktv",
        "cover_url": "https://thumbor.prod.vidiocdn.com/lJ0VbXBqgieZcVnLJ-Beck84Idk=/230x230/filters:quality(70)/vidio-web-prod-livestreaming/uploads/livestreaming/square_image/5415/802b76.png"
      },
      {
        "content_id": "18105",
        "nama_channel": "GGS TV",
        "cover_url": "https://thumbor.prod.vidiocdn.com/mKMJ1J-ffUe8NpZ3ky3Ve5oDzuI=/230x230/filters:quality(70)/vidio-web-prod-livestreaming/uploads/livestreaming/square_image/18105/25d569.png"
      },
      {
        "content_id": "19046",
        "nama_channel": "Sin Po TV",
        "cover_url": "https://thumbor.prod.vidiocdn.com/j6L0yLX8CtZTUnIO5aMzs0tNkvI=/230x230/filters:quality(70)/vidio-web-prod-livestreaming/uploads/livestreaming/square_image/19046/aaa3fa.png"
      },
      {
        "content_id": "7464",
        "nama_channel": "AJWA TV",
        "cover_url": "https://thumbor.prod.vidiocdn.com/GydAc8ocolWIwQ2A_1xFv0iQ3GM=/230x230/filters:quality(70)/vidio-web-prod-livestreaming/uploads/livestreaming/square_image/7464/e69965.png"
      },
      {
        "content_id": "7052",
        "nama_channel": "Hip Hip Horee!",
        "cover_url": "https://thumbor.prod.vidiocdn.com/EOkH5JDfHzAnCeGKEXiY12G36Qw=/230x230/filters:quality(70)/vidio-web-prod-livestreaming/uploads/livestreaming/square_image/7052/63032e.png"
      },
      {
        "content_id": "7432",
        "nama_channel": "Nusantara TV",
        "cover_url": "https://thumbor.prod.vidiocdn.com/npPL9VlWMJ5owmeupR7ucPjdGl4=/230x230/filters:quality(70)/vidio-web-prod-livestreaming/uploads/livestreaming/square_image/7432/bfecbc.png"
      },
      {
        "content_id": "9713",
        "nama_channel": "JTV",
        "cover_url": "https://thumbor.prod.vidiocdn.com/RFPy_yTRC9PPPbHGeJlLQgt-RaE=/230x230/filters:quality(70)/vidio-web-prod-livestreaming/uploads/livestreaming/square_image/9713/a11faf.png"
      },
      {
        "content_id": "6397",
        "nama_channel": "Horee",
        "cover_url": "https://thumbor.prod.vidiocdn.com/lfyNbk-BG70u8ahFpO9I0HhV3bM=/230x230/filters:quality(70)/vidio-web-prod-livestreaming/uploads/livestreaming/square_image/6397/d422cd.png"
      },
      {
        "content_id": "7619",
        "nama_channel": "MUSICA",
        "cover_url": "https://thumbor.prod.vidiocdn.com/I6siEUUN1ga4mYcu0Ysr9BlHeH4=/230x230/filters:quality(70)/vidio-web-prod-livestreaming/uploads/livestreaming/square_image/7619/379f71.png"
      },
      {
        "content_id": "6482",
        "nama_channel": "DAAI TV",
        "cover_url": "https://thumbor.prod.vidiocdn.com/0r_rhIVANc6dsGvQ76616ZSqF04=/230x230/filters:quality(70)/vidio-web-prod-livestreaming/uploads/livestreaming/square_image/6482/e83fcf.png"
      },
      {
        "content_id": "9714",
        "nama_channel": "jawaposTV",
        "cover_url": "https://thumbor.prod.vidiocdn.com/yo9zkfT4I-17_keD5cai7XRKEE0=/230x230/filters:quality(70)/vidio-web-prod-livestreaming/uploads/livestreaming/square_image/9714/5a2fad.jpg"
      },
      {
        "content_id": "6898",
        "nama_channel": "U-Channel TV",
        "cover_url": "https://thumbor.prod.vidiocdn.com/yw_pUKLmZyf5rwqDqh-FvU2llv8=/230x230/filters:quality(70)/vidio-web-prod-livestreaming/uploads/livestreaming/square_image/6898/7e119a.png"
      },
      {
        "content_id": "7230",
        "nama_channel": "Magna TV",
        "cover_url": "https://thumbor.prod.vidiocdn.com/43T_Bt_R_JSQugV3MxoAeYze7OQ=/230x230/filters:quality(70)/vidio-web-prod-livestreaming/uploads/livestreaming/square_image/7230/7d6bf5.jpg"
      },
      {
        "content_id": "12607",
        "nama_channel": "DMI TV",
        "cover_url": "https://thumbor.prod.vidiocdn.com/XudiSJe7FNdZ4dBfDmy-5X0MwZo=/230x230/filters:quality(70)/vidio-web-prod-livestreaming/uploads/livestreaming/square_image/12607/de1855.png"
      },
      {
        "content_id": "9182",
        "nama_channel": "CTV 5",
        "cover_url": "https://thumbor.prod.vidiocdn.com/yRBAoM6H7dAkEINjwCH-TVbeacE=/230x230/filters:quality(70)/vidio-web-prod-livestreaming/uploads/livestreaming/square_image/9182/13b733.png"
      },
      {
        "content_id": "9183",
        "nama_channel": "CTV 6",
        "cover_url": "https://thumbor.prod.vidiocdn.com/mlEiapp7GXmQN5-WBHtM1EY6-kM=/230x230/filters:quality(70)/vidio-web-prod-livestreaming/uploads/livestreaming/square_image/9183/33e19d.png"
      },
      {
        "content_id": "6686",
        "nama_channel": "CTV 2",
        "cover_url": "https://thumbor.prod.vidiocdn.com/czBGyoVEbdU5E64ZH88sgEfmWXg=/230x230/filters:quality(70)/vidio-web-prod-livestreaming/uploads/livestreaming/square_image/6686/14270d.png"
      },
      {
        "content_id": "6685",
        "nama_channel": "CTV 1",
        "cover_url": "https://thumbor.prod.vidiocdn.com/7chJIHmXZKn6pLd4kHzMH44577M=/230x230/filters:quality(70)/vidio-web-prod-livestreaming/uploads/livestreaming/square_image/6685/a2ed39.png"
      },
      {
        "content_id": "6786",
        "nama_channel": "CTV 3",
        "cover_url": "https://thumbor.prod.vidiocdn.com/RoE6gTfzYNnm1APnwvK_Bi7j_-Y=/230x230/filters:quality(70)/vidio-web-prod-livestreaming/uploads/livestreaming/square_image/6786/d2ebc5.png"
      },
      {
        "content_id": "6299",
        "nama_channel": "Bein 1",
        "cover_url": "https://thumbor.prod.vidiocdn.com/R5o3HOzN4coNEldIuKjnpawojr4=/230x230/filters:quality(70)/vidio-web-prod-livestreaming/uploads/livestreaming/square_image/6299/d74f54.png"
      },
      {
        "content_id": "17875",
        "nama_channel": "Bein 2",
        "cover_url": "https://thumbor.prod.vidiocdn.com/HsxPbK2T6gPnpmNmiL4KEApfzz0=/230x230/filters:quality(70)/vidio-web-prod-livestreaming/uploads/livestreaming/square_image/17875/afb4ca.png"
      },
      {
        "content_id": "6317",
        "nama_channel": "Bein 3",
        "cover_url": "https://thumbor.prod.vidiocdn.com/lKgFAcljoRcYILYnMzYh8dt7Ixw=/230x230/filters:quality(70)/vidio-web-prod-livestreaming/uploads/livestreaming/square_image/6317/4a8762.png"
      },
      {
        "content_id": "17139",
        "nama_channel": "SPOTV",
        "cover_url": "https://thumbor.prod.vidiocdn.com/1MzvDHEzp4Zo_wfPgQQzwkJOKc8=/230x230/filters:quality(70)/vidio-web-prod-livestreaming/uploads/livestreaming/square_image/17139/e5207b.png"
      },
      {
        "content_id": "17140",
        "nama_channel": "SPOTV 2",
        "cover_url": "https://thumbor.prod.vidiocdn.com/7Yaodip5SnRzHSrJqowhSrt1uSo=/230x230/filters:quality(70)/vidio-web-prod-livestreaming/uploads/livestreaming/square_image/17140/18e12a.png"
      },
      {
        "content_id": "9353",
        "nama_channel": "Premier League TV",
        "cover_url": "https://thumbor.prod.vidiocdn.com/wxu6A5xCPmydS0PsUyDZa9kbGeo=/230x230/filters:quality(70)/vidio-web-prod-livestreaming/uploads/livestreaming/square_image/9353/a79dfe.png"
      },
      {
        "content_id": "19538",
        "nama_channel": "Real Madrid TV",
        "cover_url": "https://thumbor.prod.vidiocdn.com/2x3R48h57BqxajiojvqgSbkQwCU=/230x230/filters:quality(70)/vidio-web-prod-livestreaming/uploads/livestreaming/square_image/19538/c129a3.png"
      },
      {
        "content_id": "18189",
        "nama_channel": "Champions Golf 1",
        "cover_url": "https://thumbor.prod.vidiocdn.com/5RyqXQzhOVE-gf2Y_IG1e5heJV8=/230x230/filters:quality(70)/vidio-web-prod-livestreaming/uploads/livestreaming/square_image/18189/8180b2.png"
      },
      {
        "content_id": "18190",
        "nama_channel": "Champions Golf 2",
        "cover_url": "https://thumbor.prod.vidiocdn.com/iASUDB26jxl_lTZyJTM2mmr3fQY=/230x230/filters:quality(70)/vidio-web-prod-livestreaming/uploads/livestreaming/square_image/18190/541269.png"
      },
      {
        "content_id": "6362",
        "nama_channel": "TVN",
        "cover_url": "https://thumbor.prod.vidiocdn.com/TjMKXqjCDGF1uqycTxG-Os7E87E=/230x230/filters:quality(70)/vidio-web-prod-livestreaming/uploads/livestreaming/square_image/6362/dcd434.png"
      },
      {
        "content_id": "6852",
        "nama_channel": "Makkah TV",
        "cover_url": "https://thumbor.prod.vidiocdn.com/MBL6RJmC3YxGllDHfkl-3tOYjts=/230x230/filters:quality(70)/vidio-web-prod-livestreaming/uploads/livestreaming/square_image/6852/1047bc.png"
      },
      {
        "content_id": "8121",
        "nama_channel": "Rock Action",
        "cover_url": "https://thumbor.prod.vidiocdn.com/KNwURMx7JBhbW7yXRRo9_SQUvHM=/230x230/filters:quality(70)/vidio-web-prod-livestreaming/uploads/livestreaming/square_image/8121/e9e2b9.png"
      },
      {
        "content_id": "6410",
        "nama_channel": "Aljazeera",
        "cover_url": "https://thumbor.prod.vidiocdn.com/ylPI-fG-She_OlfbH8KWncdsDe8=/230x230/filters:quality(70)/vidio-web-prod-livestreaming/uploads/livestreaming/square_image/6410/6027db.png"
      },
      {
        "content_id": "6784",
        "nama_channel": "Arirang",
        "cover_url": "https://thumbor.prod.vidiocdn.com/oBMhyILK-ywwtqBqQyt51dmDs5o=/230x230/filters:quality(70)/vidio-web-prod-livestreaming/uploads/livestreaming/square_image/6784/b9cb20.png"
      },
      {
        "content_id": "8120",
        "nama_channel": "ROCK Entertainment",
        "cover_url": "https://thumbor.prod.vidiocdn.com/evo4ygNACDOou93AiTxBSlw6wrs=/230x230/filters:quality(70)/vidio-web-prod-livestreaming/uploads/livestreaming/square_image/8120/8d7f22.png"
      },
      {
        "content_id": "6411",
        "nama_channel": "CNA",
        "cover_url": "https://thumbor.prod.vidiocdn.com/UeT72lXpCHQ7pp5YCRA-eFlsajU=/230x230/filters:quality(70)/vidio-web-prod-livestreaming/uploads/livestreaming/square_image/6411/49242c.png"
      },
      {
        "content_id": "7150",
        "nama_channel": "ABC Australia",
        "cover_url": "https://thumbor.prod.vidiocdn.com/7_vlXOuPe1jTvYQCMkgYv_KPjJQ=/230x230/filters:quality(70)/vidio-web-prod-livestreaming/uploads/livestreaming/square_image/7150/2de77e.png"
      },
      {
        "content_id": "7968",
        "nama_channel": "NHK World Japan",
        "cover_url": "https://thumbor.prod.vidiocdn.com/zxr-mrOWStozeCuL4GoW56c0JBc=/230x230/filters:quality(70)/vidio-web-prod-livestreaming/uploads/livestreaming/square_image/7968/3f44ff.png"
      },
      {
        "content_id": "5075",
        "nama_channel": "DW English",
        "cover_url": "https://thumbor.prod.vidiocdn.com/CkGuUHK9vLiapJ8s_TVp_Mj5v60=/230x230/filters:quality(70)/vidio-web-prod-livestreaming/uploads/livestreaming/square_image/5075/f6106b.png"
      },
      {
        "content_id": "6412",
        "nama_channel": "Euronews",
        "cover_url": "https://thumbor.prod.vidiocdn.com/mv4ZFcm2QaBMgaCprNUczDIaSJ4=/230x230/filters:quality(70)/vidio-web-prod-livestreaming/uploads/livestreaming/square_image/6412/c0e105.png"
      },
      {
        "content_id": "18622",
        "nama_channel": "Daystar TV",
        "cover_url": "https://thumbor.prod.vidiocdn.com/a_R11gFNIXuNsUiqJ6Tsj-45lqE=/230x230/filters:quality(70)/vidio-web-prod-livestreaming/uploads/livestreaming/square_image/18622/d20ab7.png"
      },
      {
        "content_id": "17278",
        "nama_channel": "TV5Monde",
        "cover_url": "https://thumbor.prod.vidiocdn.com/AW2JNvGveJR_JGN4sr8pcViIxNM=/230x230/filters:quality(70)/vidio-web-prod-livestreaming/uploads/livestreaming/square_image/17278/138bad.png"
      },
      {
        "content_id": "6533",
        "nama_channel": "Zoomoo",
        "cover_url": "https://thumbor.prod.vidiocdn.com/vQdbJZqHtzPPXckjO0Hy8yy-3_0=/230x230/filters:quality(70)/vidio-web-prod-livestreaming/uploads/livestreaming/square_image/6533/f6c9c0.png"
      },
      {
        "content_id": "12784",
        "nama_channel": "Africanews",
        "cover_url": "https://thumbor.prod.vidiocdn.com/gxp9cK9zfpgAKXUUuVc7SYF1q1g=/230x230/filters:quality(70)/vidio-web-prod-livestreaming/uploads/livestreaming/square_image/12784/b75a42.png"
      }
    ]
  }
}